Workbook

Sheet Component Master
A1: Categories | B1: CID/SKU Number | C1: Components | D1: Specification | E1: Vendor | F1: Last Updated Price | G1: Last Updated Date | H1: UOM | I1: Vajra | J1: Astra | K1: Bhima | L1: Vyoma | M1: Chakra | N1: Agri | O1: Availability | P1: Project 1- P0001 | Q1: Project 2- P0002 | R1: Project 3- P0003 | S1: Effective Inventory
A2: Airframe | B2: Aero0001 | C2: Carry case | D2: Bhima_Carrycase_with_Foam | E2: Aerotek | F2: 28674 | G2: 45383 | H2: Nos | I2: No | J2: No | K2: 1 | L2: No | M2: No | N2: No | O2: 2 | S2: =O2-P2-Q2-R2 -> 2
A3: Airframe | B3: Aero0002 | C3: Carry case | D3: Vajra_Carrycase_with_Foam | E3: Paxshell | F3: 23482 | G3: 45362 | H3: Nos | I3: 1 | J3: No | K3: No | L3: No | M3: No | N3: No | O3: 0 | S3: =O3-P3-Q3-R3 -> 0
A4: Airframe | B4: Aero0003 | C4: Carry case | D4: Astra Carry case with Foam | E4: Paxshell | F4: 14514 | G4: 45330 | H4: Nos | I4: No | J4: 1 | K4: No | L4: No | M4: No | N4: No | O4: 0 | S4: =O4-P4-Q4-R4 -> 0
A5: Airframe | B5: Aero0004 | C5: Carry case | D5: Agri Carry case with Foam | E5: Aerotek | F5: 32450 | G5: 45383 | H5: Nos | I5: No | J5: No | K5: No | L5: No | M5: No | N5: 1 | O5: 0 | S5: =O5-P5-Q5-R5 -> 0
A6: Airframe | B6: Aero0005 | C6: Carry case | D6: For Nano Drone | E6: Aerotek | F6: 5000 | G6: 45334 | H6: Nos | I6: No | J6: No | K6: No | L6: No | M6: 1 | N6: No | O6: 0 | S6: =O6-P6-Q6-R6 -> 0
A7: Airframe | B7: Aero0006 | C7: CF Sheet | D7: 400mm * 300mm * 1mm | E7: Hindustan Engineers | F7: 1420 | G7: 45391 | H7: Nos | I7: Project Specfic | J7: Project Specfic | K7: Project Specfic | L7: Project Specfic | M7: Project Specfic | N7: Project Specfic | O7: 1 | S7: =O7-P7-Q7-R7 -> 1
A8: Airframe | B8: Aero0007 | C8: CF Sheet | D8: 130mm * 90mm * 1mm | E8: Hindustan Engineers | F8: 138 | G8: 45406 | H8: Nos | I8: Project Specfic | J8: Project Specfic | K8: Project Specfic | L8: Project Specfic | M8: Project Specfic | N8: Project Specfic | O8: 1 | P8: 1 | S8: =O8-P8-Q8-R8 -> 0
A9: Airframe | B9: Aero0008 | C9: CF Sheet | D9: 125mm * 75mm * 3mm | E9: Hindustan Engineers | F9: 303 | G9: 45406 | H9: Nos | I9: Project Specfic | J9: Project Specfic | K9: Project Specfic | L9: Project Specfic | M9: Project Specfic | N9: Project Specfic | O9: 1 | Q9: 1 | S9: =O9-P9-Q9-R9 -> 0
A10: Airframe | B10: Aero0009 | C10: CF Sheet | D10: 300mm * 200mm * 2mm | E10: Hindustan Engineers | F10: 1291 | G10: 45406 | H10: Nos | I10: Project Specfic | J10: Project Specfic | K10: Project Specfic | L10: Project Specfic | M10: Project Specfic | N10: Project Specfic | O10: 1 | Q10: 1 | S10: =O10-P10-Q10-R10 -> 0
A11: Airframe | B11: Aero0010 | C11: CF Sheet | D11: 300mm * 200mm * 3mm | E11: Hindustan Engineers | F11: 1937 | G11: 45406 | H11: Nos | I11: Project Specfic | J11: Project Specfic | K11: Project Specfic | L11: Project Specfic | M11: Project Specfic | N11: Project Specfic | O11: 3 | Q11: 1 | S11: =O11-P11-Q11-R11 -> 2
A12: Airframe | B12: Aero0011 | C12: CF Sheet | D12: 100mm * 250mm * 4mm | E12: Hindustan Engineers | F12: 1076 | G12: 45406 | H12: Nos | I12: Project Specfic | J12: Project Specfic | K12: Project Specfic | L12: Project Specfic | M12: Project Specfic | N12: Project Specfic | O12: 2 | S12: =O12-P12-Q12-R12 -> 2
A13: Airframe | B13: Aero0012 | C13: CF Sheet | D13: 400mm * 400mm * 4mm | E13: Hindustan Engineers | F13: 6886 | G13: 45406 | H13: Nos | I13: Project Specfic | J13: Project Specfic | K13: Project Specfic | L13: Project Specfic | M13: Project Specfic | N13: Project Specfic | O13: 4 | P13: 4 | S13: =O13-P13-Q13-R13 -> 0
A14: Airframe | B14: Aero0013 | C14: CF Hollow Tube | D14: CF Tube 30mm OD * 27mm ID * 550mm | E14: Hindustan Engineers | F14: 2247 | G14: 45391 | H14: Nos | I14: No | J14: No | K14: No | L14: No | M14: No | N14: 6 | O14: 0 | S14: =O14-P14-Q14-R14 -> 0
A15: Airframe | B15: Aero0014 | C15: CF Hollow Tube | D15: CF Tube 6mm OD * 4mm ID * 1000mm | E15: Think Robotics | F15: 759.99 | G15: 45407 | H15: Nos | I15: 2 | J15: No | K15: No | L15: No | M15: No | N15: No | O15: 2 | Q15: 2 | S15: =O15-P15-Q15-R15 -> 0
A16: Airframe | B16: Aero0015 | C16: CF Square Tube | D16: CF Sq Tube 15mm * 13mm * 1000mm/Gloss | E16: Think Robotics | F16: 4399.99 | G16: 45407 | H16: Nos | I16: 2 | J16: No | K16: No | L16: No | M16: No | N16: No | O16: 2 | Q16: 2 | S16: =O16-P16-Q16-R16 -> 0
A17: Airframe | B17: Aero0016 | C17: Spacers | D17: 50 mm spacer (Pack of 20) | E17: Local | F17: 700 | G17: - | H17: Pack | I17: Yes | J17: Yes | K17: Yes | L17: No | M17: No | N17: No | O17: 1 | S17: =O17-P17-Q17-R17 -> 1
A18: Airframe | B18: Aero0017 | C18: Spacers | D18: 20mm Spacer(Pack of 25) | E18: Macfos | F18: 550 | G18: 45411 | H18: Pack | I18: Yes | J18: Yes | K18: Yes | L18: No | M18: No | N18: No | O18: 0 | S18: =O18-P18-Q18-R18 -> 0
A19: Airframe | B19: Aero0018 | C19: Spacers | D19: 10 mm spacer (Pack of 20) | E19: Local | F19: 550 | G19: - | H19: Pack | I19: Yes | J19: Yes | K19: Yes | L19: No | M19: No | N19: No | O19: 1 | S19: =O19-P19-Q19-R19 -> 1
A20: Airframe | B20: Aero0019 | C20: Spacers | D20: Spacers 40mm female to female | E20: Local | F20: 350 | G20: - | H20: Pack | I20: Yes | J20: Yes | K20: No | L20: No | M20: No | N20: No | O20: 1 | S20: =O20-P20-Q20-R20 -> 1
A21: Airframe | B21: Aero0020 | C21: Shock Absorber | D21: Pixhawk Dampner plate | E21: Macfos | F21: 144.07 | G21: 45412 | H21: Nos | I21: Yes | J21: Yes | K21: No | L21: No | M21: No | N21: 1 | O21: 1 | S21: =O21-P21-Q21-R21 -> 1
A22: Airframe | B22: Aero0021 | C22: Frame | D22: NANO-Rekon 4 FR Freestyle Frame Kit 4 Inches Frame | E22: Quadkart | F22: 7499 | G22: 45381 | H22: Nos | I22: No | J22: No | K22: No | L22: No | M22: 1 | N22: No | O22: 1 | S22: =O22-P22-Q22-R22 -> 1
A23: Airframe | B23: Aero0022 | C23: Frame | D23: M1500 | E23: T-Drones | F23: 450000 | G23: 45342 | H23: Nos | I23: No | J23: No | K23: 1 | L23: No | M23: No | N23: No | O23: 2 | S23: =O23-P23-Q23-R23 -> 2
A24: Airframe | B24: Aero0023 | C24: Frame | D24: M690 Pro | E24: T-Drones | F24: 210000 | G24: 45339 | H24: Nos | I24: No | J24: 1 | K24: No | L24: No | M24: No | N24: No | O24: 0 | S24: =O24-P24-Q24-R24 -> 0
A25: Airframe | B25: Aero0024 | C25: Frame | D25: Vyoma Airframe | E25: Arace | F25: 1903381.9 | G25: 45308 | H25: Nos | I25: No | J25: No | K25: No | L25: 1 | M25: No | N25: No | O25: 2 | S25: =O25-P25-Q25-R25 -> 2
A26: Airframe | B26: Aero0025 | C26: Landing gear | D26: M1500 | E26: T-Drones | F26: 18765.24 | G26: 45308 | H26: Nos | I26: No | J26: No | K26: 2 | L26: No | M26: No | N26: No | O26: 4 | S26: =O26-P26-Q26-R26 -> 4
A27: Airframe | B27: Aero0026 | C27: Manpack | D27: Waterproof manpack | E27: Aerotek | F27: 13750 | G27: 45339 | H27: Nos | I27: No | J27: No | K27: No | L27: 1 | M27: No | N27: No | O27: 2 | S27: =O27-P27-Q27-R27 -> 2
A28: Airframe | B28: Aero0027 | C28: Water Jet cutting | D28: Alind water jet cutting | E28: Alind | F28: 5000 | G28: - | H28: Nos | I28: Project Specfic | J28: Project Specfic | K28: Project Specfic | L28: Project Specfic | M28: Project Specfic | N28: Project Specfic | O28: 0 | S28: =O28-P28-Q28-R28 -> 0
A29: Airframe | B29: Aero0028 | C29: 3D Printed Parts | D29: Canopy | E29: Amuse | F29: 10000 | G29: - | H29: Nos | I29: 1 | J29: No | K29: No | L29: No | M29: No | N29: 1 | O29: 0 | S29: =O29-P29-Q29-R29 -> 0
A30: Airframe | B30: Aero0029 | C30: 3D Printed Parts | D30: 3D Printed Parts | E30: Amuse | F30: 30000 | G30: - | H30: Nos | I30: Project Specfic | J30: Project Specfic | K30: Project Specfic | L30: Project Specfic | M30: Project Specfic | N30: Project Specfic | O30: 0 | S30: =O30-P30-Q30-R30 -> 0
A31: Communication | B31: Aero0030 | C31: Remote controller | D31: Skydroid H12 | E31: Robokits | F31: 30421.58 | G31: 45391 | H31: Nos | I31: Yes | J31: No | K31: No | L31: No | M31: No | N31: 1 | O31: 0 | S31: =O31-P31-Q31-R31 -> 0
A32: Communication | B32: Aero0031 | C32: Remote controller | D32: SIYI MK15 AGRI Version | E32: Robokits | F32: 48287.96 | G32: 45414 | H32: Nos | I32: No | J32: No | K32: No | L32: No | M32: No | N32: 1 | O32: 2 | P32: 2 | S32: =O32-P32-Q32-R32 -> 0
A33: Communication | B33: Aero0032 | C33: Remote controller | D33: Logitech Joystick | E33: Local | F33: 2500 | G33: - | H33: Nos | I33: Yes | J33: Yes | K33: No | L33: Yes | M33: No | N33: No | O33: 2 | S33: =O33-P33-Q33-R33 -> 2
A34: Communication | B34: Aero0033 | C34: Remote controller | D34: SIYI HM30 | E34: Robokits | F34: 29404.42 | G34: 45414 | H34: Nos | I34: Yes | J34: Yes | K34: No | L34: No | M34: No | N34: No | O34: 1 | S34: =O34-P34-Q34-R34 -> 1
A35: Communication | B35: Aero0034 | C35: Remote controller | D35: Skydroid H16 | E35: Indian Robo Store | F35: 89999 | G35: 45414 | H35: Nos | I35: Yes | J35: Yes | K35: Yes | L35: Yes | M35: No | N35: No | O35: 3 | S35: =O35-P35-Q35-R35 -> 3
A36: Communication | B36: Aero0035 | C36: Remote controller | D36: Skydroid H16 Pro | E36: Indian Robo Store | F36: 138999 | G36: 45414 | H36: Nos | I36: Yes | J36: Yes | K36: Yes | L36: Yes | M36: No | N36: No | O36: 0 | S36: =O36-P36-Q36-R36 -> 0
A37: Communication | B37: Aero0036 | C37: Remote controller | D37: SIYI MK15 | E37: Indian Robo Store | F37: 79999 | G37: 45414 | H37: Nos | I37: Yes | J37: Yes | K37: Yes | L37: Yes | M37: No | N37: No | O37: 1 | S37: =O37-P37-Q37-R37 -> 1
A38: Communication | B38: Aero0037 | C38: Remote controller | D38: Skydroid T12 | E38: Indian Robo Store | F38: 23999 | G38: 45414 | H38: Nos | I38: Yes | J38: Yes | K38: Yes | L38: Yes | M38: No | N38: 1 | O38: 0 | S38: =O38-P38-Q38-R38 -> 0
A39: Communication | B39: Aero0038 | C39: RF communication | D39: Doodle Labs RM-2450-12M3 | E39: Aqtronics | F39: 209632.9 | G39: 45381 | H39: Nos | I39: Yes | J39: Yes | K39: No | L39: 3 | M39: No | N39: No | O39: 6 | S39: =O39-P39-Q39-R39 -> 6
A40: Communication | B40: Aero0039 | C40: RF communication | D40: Evaluation Kit | E40: Aqtronics | F40: 41134.46 | G40: 45381 | H40: Nos | I40: Yes | J40: Yes | K40: No | L40: 3 | M40: No | N40: No | O40: 6 | S40: =O40-P40-Q40-R40 -> 6
A41: Communication | B41: Aero0040 | C41: Remote controller | D41: Herelink Transmitter | E41: Gadgets Deal | F41: 85000 | G41: 45414 | H41: Nos | I41: Yes | J41: Yes | K41: Yes | L41: Yes | M41: No | N41: No | O41: 1 | S41: =O41-P41-Q41-R41 -> 1
A42: Communication | B42: Aero0041 | C42: Remote controller | D42: FrSky 2.4GHz Taranis Q X7 Access Transmitter - Black | E42: Indian Robo Store | F42: 15900 | G42: 45414 | H42: Nos | I42: Yes | J42: Yes | K42: No | L42: Yes | M42: 1 | N42: No | O42: 1 | S42: =O42-P42-Q42-R42 -> 1
A43: Electricals | B43: Aero0042 | C43: Propellers | D43: Vajra Props 1760_with_mount | E43: Indian Robo Store | F43: 3499 | G43: 45363 | H43: Set | I43: 3 | J43: No | K43: No | L43: No | M43: No | N43: No | O43: 2 | S43: =O43-P43-Q43-R43 -> 2
A44: Electricals | B44: Aero0043 | C44: Propellers | D44: T- motor P18*6.1 Prop-2PCS/PAIR | E44: Macfos | F44: 10305 | G44: 45411 | H44: Set | I44: No | J44: 3 | K44: No | L44: No | M44: No | N44: No | O44: 6 | S44: =O44-P44-Q44-R44 -> 6
A45: Electricals | B45: Aero0044 | C45: Propellers | D45: GEMFAN 5.2*2.5 | E45: DRK Store | F45: 1299 | G45: 45330 | H45: Set | I45: No | J45: No | K45: No | L45: No | M45: 1 | N45: No | O45: 1 | S45: =O45-P45-Q45-R45 -> 1
A46: Electricals | B46: Aero0045 | C46: Propellers | D46: Gemfan hurricane 4024 2-blade-propeller-1-5mm-shaft-set-of-8 | E46: DRK Store | F46: 1999 | G46: 45330 | H46: Set | I46: No | J46: No | K46: No | L46: No | M46: 1 | N46: No | O46: 1 | S46: =O46-P46-Q46-R46 -> 1
A47: Electricals | B47: Aero0046 | C47: Propellers | D47: NS18*6 propellers | E47: Macfos | F47: 8394 | G47: 45330 | H47: Set | I47: No | J47: 3 | K47: No | L47: No | M47: No | N47: No | O47: 2 | S47: =O47-P47-Q47-R47 -> 2
A48: Electricals | B48: Aero0047 | C48: Propellers | D48: 30*10 inch Propellers | E48: T-Drones | F48: 68700 | G48: 45330 | H48: Set | I48: No | J48: No | K48: 3 | L48: No | M48: No | N48: No | O48: 10 | S48: =O48-P48-Q48-R48 -> 10
A49: Electricals | B49: Aero0048 | C49: Battery | D49: 6S_30000mah_Mpower | E49: Mpower | F49: 48500 | G49: 45361 | H49: Nos | I49: No | J49: No | K49: No | L49: 2 | M49: No | N49: No | O49: 4 | S49: =O49-P49-Q49-R49 -> 4
A50: Electricals | B50: Aero0049 | C50: Battery | D50: 6S 22000mAh Solid State | E50: Mpower | F50: 29500 | G50: 45635 | H50: Nos | I50: Yes | J50: 1 | K50: 4 | L50: No | M50: No | N50: No | O50: 3 | R50: 2 | S50: =O50-P50-Q50-R50 -> 1
A51: Electricals | B51: Aero0050 | C51: Battery | D51: 21000mAh | E51: Mpower | F51: 22500 | G51: 45311 | H51: Nos | I51: No | J51: No | K51: Yes | L51: No | M51: No | N51: No | O51: 4 | S51: =O51-P51-Q51-R51 -> 4
A52: Electricals | B52: Aero0051 | C52: Battery | D52: Tattu 16000mAh 6S Lipo Battery | E52: Robokits | F52: 16500 | G52: 45391 | H52: Nos | I52: No | J52: No | K52: No | L52: No | M52: No | N52: 2 | O52: 7 | P52: 4 | S52: =O52-P52-Q52-R52 -> 3
A53: Electricals | B53: Aero0052 | C53: Battery | D53: 6S 15000mAh Battery | E53: Mpower | F53: 15000 | G53: 45311 | H53: Nos | I53: Yes | J53: No | K53: No | L53: No | M53: No | N53: No | O53: 1 | S53: =O53-P53-Q53-R53 -> 1
A54: Electricals | B54: Aero0053 | C54: Battery | D54: 12600_mah | E54: Mpower | F54: 13500 | G54: 45330 | H54: Nos | I54: 2 | J54: No | K54: No | L54: No | M54: No | N54: No | O54: 0 | S54: =O54-P54-Q54-R54 -> 0
A55: Electricals | B55: Aero0054 | C55: Battery | D55: 4S 3000mAh | E55: Mpower | F55: 3000 | G55: 45330 | H55: Nos | I55: No | J55: No | K55: No | L55: No | M55: 1 | N55: No | O55: 4 | S55: =O55-P55-Q55-R55 -> 4
A56: Electricals | B56: Aero0055 | C56: Battery | D56: LG INR18650MJ1 3500mAh (3c) LI-ION BATTERY | E56: Macfos | F56: 599 | G56: 45414 | H56: Nos | I56: No | J56: No | K56: No | L56: No | M56: 2 | N56: No | O56: 2 | S56: =O56-P56-Q56-R56 -> 2
A57: Electricals | B57: Aero0056 | C57: Battery | D57: Lemon 5000mAH 4S 45C/90C Lithium Polymer Battery Pack | E57: Macfos | F57: 3449.15 | G57: 45311 | H57: Nos | I57: No | J57: No | K57: No | L57: No | M57: No | N57: No | O57: 1 | S57: =O57-P57-Q57-R57 -> 1
A58: Electricals | B58: Aero0057 | C58: Battery charger | D58: SKYRC_PC1080 | E58: Macfos | F58: 21999 | G58: 45414 | H58: Nos | I58: Yes | J58: 1 | K58: 1 | L58: 1 | M58: No | N58: 1 | O58: 3 | P58: 2 | S58: =O58-P58-Q58-R58 -> 1
A59: Electricals | B59: Aero0058 | C59: Battery charger | D59: SKYRC_PC_520 | E59: Macfos | F59: 12499 | G59: 45414 | H59: Nos | I59: Yes | J59: Yes | K59: No | L59: No | M59: 1 | N59: No | O59: 0 | S59: =O59-P59-Q59-R59 -> 0
A60: Electricals | B60: Aero0059 | C60: Battery charger | D60: HTRC C240 DUO | E60: Macfos | F60: 5499 | G60: 45414 | H60: Nos | I60: 1 | J60: Yes | K60: No | L60: No | M60: 1 | N60: No | O60: 1 | Q60: 1 | S60: =O60-P60-Q60-R60 -> 0
A61: Electricals | B61: Aero0060 | C61: Battery charger | D61: iMAX_B6AC | E61: Macfos | F61: 2399 | G61: 45414 | H61: Nos | I61: Yes | J61: Yes | K61: No | L61: No | M61: 1 | N61: No | O61: 0 | S61: =O61-P61-Q61-R61 -> 0
A62: Electricals | B62: Aero0061 | C62: Motor | D62: Tarot 4008 330kV motor | E62: Macfos | F62: 4700 | G62: 45414 | H62: Nos | I62: 4 | J62: Yes | K62: No | L62: No | M62: No | N62: No | O62: 15 | S62: =O62-P62-Q62-R62 -> 15
A63: Electricals | B63: Aero0062 | C63: Motor | D63: T MOTOR ANTIGRAVITY 4004 300KV(Pack of 2) | E63: Macfos | F63: 18762 | G63: 45414 | H63: Nos | I63: No | J63: Yes | K63: No | L63: No | M63: No | N63: No | O63: 4 | S63: =O63-P63-Q63-R63 -> 4
A64: Electricals | B64: Aero0063 | C64: Motor | D64: T-Motor MN5008 Antigravity Type 6-12S UAV Motor KV340 | E64: Macfos | F64: 7863 | G64: 45414 | H64: Nos | I64: No | J64: 4 | K64: No | L64: No | M64: No | N64: No | O64: 6 | Q64: 4 | S64: =O64-P64-Q64-R64 -> 2
A65: Electricals | B65: Aero0064 | C65: Motor | D65: Hobbywing X6 plus propulsion system | E65: Macfos | F65: 11372.84 | G65: 45414 | H65: Nos | I65: No | J65: No | K65: No | L65: No | M65: No | N65: 6 | O65: 14 | P65: 12 | S65: =O65-P65-Q65-R65 -> 2
A66: Electricals | B66: Aero0065 | C66: Motor | D66: HGLRC AEOLUS 1603 2800KV Brushless Motor | E66: Quadkart | F66: 1199 | G66: 45414 | H66: Nos | I66: No | J66: No | K66: No | L66: No | M66: 4 | N66: No | O66: 4 | S66: =O66-P66-Q66-R66 -> 4
A67: Electricals | B67: Aero0066 | C67: ESC | D67: Air 40 Amps | E67: Macfos | F67: 2800 | G67: 45414 | H67: Nos | I67: 4 | J67: No | K67: No | L67: No | M67: No | N67: No | O67: 8 | Q67: 4 | S67: =O67-P67-Q67-R67 -> 4
A68: Electricals | B68: Aero0067 | C68: Cables | D68: High Quality Ultra Flexible 16AWG Silicon Wire 5m (Red) | E68: Macfos | F68: 599 | G68: 45414 | H68: Nos | I68: 1 | J68: 1 | K68: 1 | L68: Yes | M68: No | N68: 1 | O68: 1 | S68: =O68-P68-Q68-R68 -> 1
A69: Electricals | B69: Aero0068 | C69: Cables | D69: High Quality Ultra Flexible 16AWG Silicon Wire 5m (Black) | E69: Macfos | F69: 599 | G69: 45414 | H69: Nos | I69: 1 | J69: 1 | K69: 1 | L69: Yes | M69: No | N69: 1 | O69: 1 | S69: =O69-P69-Q69-R69 -> 1
A70: Electricals | B70: Aero0069 | C70: BEC | D70: Matek MICRO BEC 5V/12V-ADJ | E70: Macfos | F70: 585 | G70: 45414 | H70: Nos | I70: Yes | J70: Yes | K70: 1 | L70: Yes | M70: No | N70: No | O70: 0 | S70: =O70-P70-Q70-R70 -> 0
A71: Electricals | B71: Aero0070 | C71: BEC | D71: ReadytoSky 2-6S 5V/3A | E71: Macfos | F71: 240 | G71: 45414 | H71: Nos | I71: 1 | J71: Yes | K71: Yes | L71: Yes | M71: No | N71: No | O71: 5 | S71: =O71-P71-Q71-R71 -> 5
A72: Electricals | B72: Aero0071 | C72: Cables | D72: High Quality Ultra Flexible 12AWG Silicone Wire 1m (Red) + 1m (Black) | E72: Macfos | F72: 599 | G72: 45414 | H72: Nos | I72: 1 | J72: 1 | K72: 1 | L72: Yes | M72: No | N72: No | O72: 1 | S72: =O72-P72-Q72-R72 -> 1
A73: Electricals | B73: Aero0072 | C73: Cables | D73: High Quality 1-8S Battery Voltage Checker & Low Voltage Buzzer Alarm | E73: Macfos | F73: 135 | G73: 45414 | H73: Nos | I73: 1 | J73: 1 | K73: 1 | L73: 1 | M73: 1 | N73: 1 | O73: 7 | P73: 2 | S73: =O73-P73-Q73-R73 -> 5
A74: Electricals | B74: Aero0073 | C74: Connectors | D74: Amass XT-90 Male-Female Connector with Housing-1Pair | E74: Macfos | F74: 95.99 | G74: 45414 | H74: Nos | I74: No | J74: No | K74: 2 | L74: Yes | M74: No | N74: 1 | O74: 20 | S74: =O74-P74-Q74-R74 -> 20
A75: Electricals | B75: Aero0074 | C75: Connectors | D75: Amass XT30-U Female Bullet Connector | E75: Macfos | F75: 29 | G75: 45414 | H75: Nos | I75: 5 | J75: 5 | K75: 5 | L75: 5 | M75: 1 | N75: 1 | O75: 20 | S75: =O75-P75-Q75-R75 -> 20
A76: Electricals | B76: Aero0075 | C76: Connectors | D76: Amass XT30U Male Bullet Connector | E76: Macfos | F76: 29 | G76: 45414 | H76: Nos | I76: 5 | J76: 5 | K76: 5 | L76: 5 | M76: 1 | N76: 1 | O76: 20 | P76: 8 | S76: =O76-P76-Q76-R76 -> 12
A77: Electronics | B77: Aero0076 | C77: Sensors | D77: PX4 Flow Sensor | E77: Macfos | F77: 15656.25 | G77: 45414 | H77: Nos | I77: Yes | J77: Yes | K77: No | L77: No | M77: No | N77: No | O77: 1 | S77: =O77-P77-Q77-R77 -> 1
A78: Electronics | B78: Aero0077 | C78: Receiver | D78: R9M 2019 Module and R9MINI OTA | E78: Macfos | F78: 6070 | G78: 45414 | H78: Nos | I78: No | J78: No | K78: No | L78: No | M78: No | N78: No | O78: 0 | S78: =O78-P78-Q78-R78 -> 0
A79: Electronics | B79: Aero0078 | C79: Sensors | D79: seagull rec | E79: Macfos | F79: 8500 | G79: 45414 | H79: Nos | I79: No | J79: Yes | K79: No | L79: No | M79: No | N79: No | O79: 1 | S79: =O79-P79-Q79-R79 -> 1
A80: Electronics | B80: Aero0079 | C80: Sensors | D80: Liquid Level sensor | E80: Macfos | F80: 2699.1 | G80: 45323 | H80: Nos | I80: No | J80: Yes | K80: No | L80: No | M80: No | N80: No | O80: 1 | S80: =O80-P80-Q80-R80 -> 1
A81: Electronics | B81: Aero0080 | C81: SD card | D81: 256 GB (Extreme) | E81: Macfos | F81: 2999 | G81: 45414 | H81: Nos | I81: Project Specfic | J81: Project Specfic | K81: Project Specfic | L81: Project Specfic | M81: Project Specfic | N81: Project Specfic | O81: 2 | S81: =O81-P81-Q81-R81 -> 2
A82: Electronics | B82: Aero0081 | C82: SD card | D82: 64 GB CARD | E82: Macfos | F82: 599 | G82: 45414 | H82: Nos | I82: Project Specfic | J82: Project Specfic | K82: Project Specfic | L82: Project Specfic | M82: Project Specfic | N82: Project Specfic | O82: 0 | S82: =O82-P82-Q82-R82 -> 0
A83: Electronics | B83: Aero0082 | C83: Cables | D83: USB C to HDMI Cable | E83: Macfos | F83: 2999 | G83: 45414 | H83: Nos | I83: 1 | J83: 1 | K83: 1 | L83: 1 | M83: 1 | N83: No | O83: 1 | S83: =O83-P83-Q83-R83 -> 1
A84: Electronics | B84: Aero0083 | C84: BEC | D84: 2-13s UBEC | E84: Macfos | F84: 620 | G84: 45359 | H84: Nos | I84: Yes | J84: Yes | K84: Yes | L84: Yes | M84: No | N84: No | O84: 5 | S84: =O84-P84-Q84-R84 -> 5
A85: Electronics | B85: Aero0084 | C85: Cables | D85: Micro USB Cable | E85: Macfos | F85: 499 | G85: 45414 | H85: Nos | I85: 1 | J85: 1 | K85: 1 | L85: 1 | M85: 1 | N85: No | O85: 1 | S85: =O85-P85-Q85-R85 -> 1
A86: Electronics | B86: Aero0085 | C86: Cables | D86: Type A to Type C | E86: Macfos | F86: 999 | G86: 45414 | H86: Nos | I86: 1 | J86: 1 | K86: 1 | L86: 1 | M86: No | N86: No | O86: 1 | S86: =O86-P86-Q86-R86 -> 1
A87: Electronics | B87: Aero0086 | C87: PDB | D87: 100A Power distribtution Board | E87: Macfos | F87: 120 | G87: 45414 | H87: Nos | I87: 1 | J87: Yes | K87: No | L87: No | M87: 1 | N87: 1 | O87: 2 | Q87: 2 | S87: =O87-P87-Q87-R87 -> 0
A88: Electronics | B88: Aero0087 | C88: Flight Controller | D88: PIXHAWK_CUBE Orange+ with ADSB Set | E88: Vyom Drones | F88: 33332 | G88: 45499 | H88: Nos | I88: 1 | J88: 1 | K88: 1 | L88: 1 | M88: No | N88: 1 | O88: 5 | P88: 2 | S88: =O88-P88-Q88-R88 -> 3
A89: Electronics | B89: Aero0088 | C89: Flight Controller | D89: Mini Carrier Board | E89: Vyom Drones | F89: 8570 | G89: 45499 | H89: Nos | I89: Yes | J89: Yes | K89: Yes | L89: No | M89: No | N89: No | O89: 2 | S89: =O89-P89-Q89-R89 -> 2
A90: Electronics | B90: Aero0089 | C90: Flight Controller | D90: Holybro Kakute H7 V2 Stack | E90: Macfos | F90: 8810 | G90: 45499 | H90: Nos | I90: No | J90: No | K90: No | L90: No | M90: 1 | N90: No | O90: 2 | S90: =O90-P90-Q90-R90 -> 2
A91: Electronics | B91: Aero0090 | C91: Flight Controller | D91: Pixhawk_2.4.8 | E91: Macfos | F91: 11296 | G91: 45499 | H91: Nos | I91: Yes | J91: Yes | K91: Yes | L91: 1 | M91: No | N91: No | O91: 0 | S91: =O91-P91-Q91-R91 -> 0
A92: Electronics | B92: Aero0091 | C92: Flight Controller | D92: JIYI K++ V2 | E92: RC Mumbai | F92: 33984 | G92: 45499 | H92: Nos | I92: No | J92: No | K92: No | L92: No | M92: No | N92: 1 | O92: 0 | S92: =O92-P92-Q92-R92 -> 0
A93: Electronics | B93: Aero0092 | C93: GPS | D93: Here3+ | E93: Macfos | F93: 24500 | G93: 45499 | H93: Nos | I93: 1 | J93: 1 | K93: 2 | L93: No | M93: No | N93: 1 | O93: 5 | P93: 2 | S93: =O93-P93-Q93-R93 -> 3
A94: Electronics | B94: Aero0093 | C94: GPS | D94: Ready to sky BN-880 GPS Module | E94: Macfos | F94: 2172 | G94: 45499 | H94: Nos | I94: No | J94: No | K94: No | L94: No | M94: 1 | N94: No | O94: 2 | S94: =O94-P94-Q94-R94 -> 2
A95: Electronics | B95: Aero0094 | C95: Sensors | D95: TF-02_LIDAR | E95: Macfos | F95: 6579 | G95: 45414 | H95: Nos | I95: Project Specfic | J95: Project Specfic | K95: Project Specfic | L95: Project Specfic | M95: No | N95: Project Specfic | O95: 0 | S95: =O95-P95-Q95-R95 -> 0
A96: Electronics | B96: Aero0095 | C96: Sensors | D96: Holybro_MS4525DO_Digital_Airspeed_Sensor | E96: Macfos | F96: 4404 | G96: 45414 | H96: Nos | I96: Project Specfic | J96: Project Specfic | K96: Project Specfic | L96: Project Specfic | M96: No | N96: Project Specfic | O96: 0 | S96: =O96-P96-Q96-R96 -> 0
A97: Electronics | B97: Aero0096 | C97: Sensors | D97: TF mini Plus | E97: Macfos | F97: 3499 | G97: 45414 | H97: Nos | I97: Project Specfic | J97: Project Specfic | K97: Project Specfic | L97: Project Specfic | M97: No | N97: Project Specfic | O97: 0 | S97: =O97-P97-Q97-R97 -> 0
A98: Electronics | B98: Aero0097 | C98: Sensors | D98: TF mini LIDAR | E98: Macfos | F98: 3269 | G98: 45414 | H98: Nos | I98: Project Specfic | J98: Project Specfic | K98: Project Specfic | L98: Project Specfic | M98: No | N98: Project Specfic | O98: 1 | S98: =O98-P98-Q98-R98 -> 1
A99: Electronics | B99: Aero0098 | C99: Sensors | D99: Obstacle Avoidance Sensor | E99: Indian Robo Store | F99: 24999 | G99: 45411 | H99: Nos | I99: Project Specfic | J99: Project Specfic | K99: Project Specfic | L99: Project Specfic | M99: No | N99: Project Specfic | O99: 1 | S99: =O99-P99-Q99-R99 -> 1
A100: Electronics | B100: Aero0099 | C100: Sensors | D100: Terrain following sensor | E100: Indian Robo Store | F100: 29999 | G100: 45411 | H100: Nos | I100: Project Specfic | J100: Project Specfic | K100: Project Specfic | L100: Project Specfic | M100: No | N100: Project Specfic | O100: 0 | S100: =O100-P100-Q100-R100 -> 0
...

Sheet Order Tracker
A1: S.No | B1: Date | C1: PO # | D1: CID/SKU Number | E1: Description | F1: Qty | G1: Vendor | H1: Unit Price | I1: Sub Total | J1: GST | K1: Shipping | L1: Total Price | M1: Quote | N1: Project | O1: Status | P1: Warranty terms | Q1: Remarks
A2: 1 | B2: 45425 | D2: Aero0170 | E2: EFT E610P Airframe with 10L Tank | F2: 1 | G2: Macfos | H2: 38903.81 | I2: =F2*H2 -> 38903.81 | J2: =0.05*I2 -> 1945.1905 | K2: 600 | L2: =SUM(I2:K2) -> 41449.001 | M2: Link | N2: NRSC | O2: Received
A3: 2 | B3: 45425 | D3: Aero0171 | E3: =VLOOKUP(D3,'Component Master'!B:D,3,0) -> CF Sheet 500*500mm*3mm | F3: 2 | G3: Macfos | H3: 7316.95 | I3: =F3*H3 -> 14633.9 | J3: =0.18*I3 -> 2634.102 | K3: 600 | L3: =SUM(I3:K3) -> 17868.002 | M3: Link | N3: AGRI-P0001 | O3: Received
A4: 3 | B4: 45425 | D4: Aero0162 | E4: =VLOOKUP(D4,'Component Master'!B:D,3,0) -> 400mm*380mm*3mm | F4: 2 | G4: Hindustan Engineers | H4: 4907 | I4: =F4*H4 -> 9814 | J4: =0.18*I4 -> 1766.52 | K4: 0 | L4: =SUM(I4:K4) -> 11580.52 | M4: Link | N4: AGRI-P0001 | O4: Received
A5: 4 | B5: 45425 | D5: - | E5: Customization & Setup of Trans-receiver | F5: 1 | G5: Apico | H5: 75000 | I5: =F5*H5 -> 75000 | J5: =0.18*I5 -> 13500 | K5: 0 | L5: =SUM(I5:K5) -> 88500 | M5: Link | N5: AGRI-P0001 | O5: Received
A6: 5 | B6: 45425 | D6: Aero0169 | E6: Drone Trans-receiver | F6: 2 | G6: Apico | H6: 38000 | I6: =F6*H6 -> 76000 | J6: =0.18*I6 -> 13680 | K6: 0 | L6: =SUM(I6:K6) -> 89680 | M6: Link | N6: AGRI-P0001 | O6: Received
A7: 6 | B7: 45426 | D7: Aero0172 | E7: Aluminium mount | F7: 12 | G7: Aerotek | H7: 4000 | I7: =F7*H7 -> 48000 | J7: =0.18*I7 -> 8640 | K7: 0 | L7: =SUM(I7:K7) -> 56640 | M7: Link | N7: AGRI-P0001 | O7: Received
A8: 7 | B8: 45426 | D8: Aero0173 | E8: Hall Sensor | F8: 3 | G8: Vyom Drones | H8: 4420 | I8: =F8*H8 -> 13260 | J8: =0.05*I8 -> 663 | K8: 0 | L8: =SUM(I8:K8) -> 13923 | M8: Link | N8: AGRI-P0001 | O8: Received
A9: 8 | B9: 45427 | D9: Aero0181 | E9: Mauch 084: 4-14S BEC | F9: 2 | G9: Vyom Drones | H9: 3900 | I9: =F9*H9 -> 7800 | J9: =0.05*I9 -> 390 | K9: 0 | L9: =SUM(I9:K9) -> 8190 | M9: Link | N9: AGRI-P0001 | O9: Received
A10: 9 | B10: 45427 | D10: Aero0182 | E10: Mauch 086: Adapter cable for Pixhawk 2 | F10: 2 | G10: Vyom Drones | H10: 500 | I10: =F10*H10 -> 1000 | J10: =0.05*I10 -> 50 | K10: 0 | L10: =SUM(I10:K10) -> 1050 | M10: Link | N10: AGRI-P0001 | O10: Received
A11: 10 | B11: 45427 | D11: Aero0183 | E11: Water flow sensor-White | F11: 2 | G11: Macfos | H11: 224 | I11: =F11*H11 -> 448 | J11: 0 | K11: =49+25 -> 74 | L11: =SUM(I11:K11) -> 522 | M11: Link | N11: AGRI-P0001 | O11: Received | Q11: Online order/COD
A12: 11 | B12: 45428 | D12: Aero0029 | E12: Lug Connector | F12: 2 | G12: Amuse | H12: 282.9 | I12: =F12*H12 -> 565.8 | J12: =0.18*I12 -> 101.844 | K12: 0 | L12: =SUM(I12:K12) -> 667.644 | M12: Link | N12: AGRI-P0001 | O12: Received
A13: 12 | B13: 45428 | D13: Aero0029 | E13: PCB Enclosure | F13: 2 | G13: Amuse | H13: 2492.8 | I13: =F13*H13 -> 4985.6 | J13: =0.18*I13 -> 897.408 | K13: 0 | L13: =SUM(I13:K13) -> 5883.008 | M13: Link | N13: AGRI-P0001 | O13: Received
A14: 13 | B14: 45429 | D14: Aero0029 | E14: Canopy | F14: 1 | G14: Nextgen | H14: 21750 | I14: =F14*H14 -> 21750 | J14: =0.18*I14 -> 3915 | K14: 100 | L14: =SUM(I14:K14) -> 25765 | M14: Link | N14: AGRI-P0001 | O14: Received
A15: 14 | B15: 45429 | D15: Aero0029 | E15: Sidewall | F15: 1 | G15: Nextgen | H15: 6300 | I15: =F15*H15 -> 6300 | J15: =0.18*I15 -> 1134 | K15: 100 | L15: =SUM(I15:K15) -> 7534 | M15: Link | N15: AGRI-P0001 | O15: Received
A16: 15 | B16: 45429 | D16: - | E16: Calibration Testing(NABL certification) | F16: 1 | G16: Dynamic Calibration | H16: 5900 | I16: =F16*H16 -> 5900 | J16: =0.18*I16 -> 1062 | K16: 0 | L16: =SUM(I16:K16) -> 6962 | M16: Link | N16: AGRI-P0001 | O16: Received
A17: 16 | B17: 45434 | D17: Aero0027 | E17: =VLOOKUP(D17,'Component Master'!B6:D189,3,0) -> Alind water jet cutting | F17: 2 | G17: Alind | H17: 1079 | I17: =F17*H17 -> 2158 | J17: =0.12*I17 -> 258.96 | K17: 0 | L17: =SUM(I17:K17) -> 2416.96 | M17: Link | N17: AGRI-P0001 | O17: Received
A18: 17 | B18: 45434 | D18: Aero0027 | E18: =VLOOKUP(D18,'Component Master'!B7:D190,3,0) -> Alind water jet cutting | F18: 2 | G18: Alind | H18: 1100 | I18: =F18*H18 -> 2200 | J18: =0.12*I18 -> 264 | K18: 0 | L18: =SUM(I18:K18) -> 2464 | M18: Link | N18: AGRI-P0001 | O18: Received
A19: 18 | B19: 45435 | D19: Aero0184 | E19: =VLOOKUP(D19,'Component Master'!B8:D191,3,0) -> Liquid water Level sensor | F19: 3 | G19: Macfos | H19: 508.47 | I19: =F19*H19 -> 1525.41 | J19: =0.18*I19 -> 274.5738 | K19: 62 | L19: =SUM(I19:K19) -> 1861.9838 | M19: Link | N19: AGRI-P0001 | O19: Received
A20: 19 | B20: 45435 | D20: Aero0183 | E20: =VLOOKUP(D20,'Component Master'!B9:D192,3,0) -> Water flow sensor-White | F20: 1 | G20: Macfos | H20: 224 | I20: =F20*H20 -> 224 | J20: 0 | K20: 62 | L20: =SUM(I20:K20) -> 286 | M20: Link | N20: AGRI-P0001 | O20: Received
A21: 20 | B21: 45435 | D21: Aero0004 | E21: =VLOOKUP(D21,'Component Master'!B2:D194,3,0) -> Agri Carry case with Foam | F21: 2 | G21: Aerotek | H21: 10750 | I21: =F21*H21 -> 21500 | J21: =0.18*I21 -> 3870 | K21: 0 | L21: =SUM(I21:K21) -> 25370 | M21: Link | N21: AGRI-P0001 | O21: Received
A22: 21 | B22: 45435 | D22: Aero0180 | E22: =VLOOKUP(D22,'Component Master'!B3:D195,3,0) -> GPS Stand-Agri | F22: 2 | G22: Elecdrone Technologies | H22: 380 | I22: =F22*H22 -> 760 | J22: =0.05*I22 -> 38 | K22: 0 | L22: =SUM(I22:K22) -> 798 | M22: Link | N22: AGRI-P0001 | O22: Received
A23: 22 | B23: 45435 | D23: Aero0172 | E23: =VLOOKUP(D23,'Component Master'!B4:D196,3,0) -> Aluminium mount | F23: 12 | G23: Aerotek | H23: 2750 | I23: =F23*H23 -> 33000 | J23: 6048 | K23: 600 | L23: =SUM(I23:K23) -> 39648 | M23: Link | N23: AGRI-P0001 | O23: Received
A24: 23 | B24: 45435 | D24: Aero0110 | E24: =VLOOKUP(D24,'Component Master'!B5:D197,3,0) -> Pump,Nozzle,Hose & Pneumatic Connectors | F24: 1 | G24: Elecdrone Technologies | H24: 6048 | I24: =F24*H24 -> 6048 | J24: =0.05*I24 -> 302.4 | K24: 0 | L24: =SUM(I24:K24) -> 6350.4 | M24: Link | N24: AGRI-P0001 | O24: Received
A25: 24 | B25: 45436 | C25: 03/24-25 | D25: Aero0029 | E25: Canopy | F25: 1 | G25: Monotech | H25: 16425 | I25: =F25*H25 -> 16425 | J25: =0.18*I25 -> 2956.5 | K25: 0 | L25: =SUM(I25:K25) -> 19381.5 | M25: Link | N25: AGRI-P0001 | O25: Received
A26: 25 | B26: 45436 | D26: Aero0027 | E26: =VLOOKUP(D26,'Component Master'!B7:D199,3,0) -> Alind water jet cutting | F26: 1 | G26: Alind | H26: 1100 | I26: =F26*H26 -> 1100 | J26: =0.12*I26 -> 132 | K26: 0 | L26: =SUM(I26:K26) -> 1232 | M26: Link | N26: AGRI-P0001 | O26: Received
A27: 26 | B27: 45436 | D27: Aero0185 | E27: =VLOOKUP(D27,'Component Master'!B8:D200,3,0) -> QS8-S Anti spark Male/Female connector pair | F27: 2 | G27: Macfos | H27: 669 | I27: =F27*H27 -> 1338 | J27: 0 | K27: 0 | L27: =SUM(I27:K27) -> 1338 | M27: Link | N27: AGRI-P0001 | O27: Received
A28: 27 | B28: 45439 | D28: - | E28: MX860 | F28: 1 | G28: T-Drones | H28: 249961.4 | I28: =F28*H28 -> 249961.4 | J28: 0 | K28: 0 | L28: =SUM(I28:K28) -> 249961.4 | M28: Link | O28: - | Q28: For Price validation
A29: 28 | B29: 45439 | D29: - | E29: M1200 | F29: 1 | G29: T-Drones | H29: 241626.58 | I29: =F29*H29 -> 241626.58 | J29: 0 | K29: 0 | L29: =SUM(I29:K29) -> 241626.58 | M29: Link | O29: - | Q29: For Price validation
A30: 29 | B30: 45439 | D30: Aero0029 | E30: Bottom Plate-sensor Holder | F30: 2 | G30: Amuse | H30: =425.7 -> 425.7 | I30: =F30*H30 -> 851.4 | J30: 188.34 | K30: 225 | L30: =SUM(I30:K30) -> 1264.74 | M30: Link | N30: AGRI-P0001 | O30: Received
A31: 30 | B31: 45439 | D31: Aero0029 | E31: Top Plate- Sensor Holder | F31: 2 | G31: Amuse | H31: 395.6 | I31: =F31*H31 -> 791.2 | J31: 188.34 | K31: 225 | L31: =SUM(I31:K31) -> 1204.54 | M31: Link | N31: AGRI-P0001 | O31: Received
A32: 31 | B32: 45439 | D32: Aero0029 | E32: Canopy | F32: 2 | G32: Nextgen | H32: 21920 | I32: =F32*H32 -> 43840 | J32: =0.18*I32 -> 7891.2 | K32: 118 | L32: =SUM(I32:K32) -> 51849.2 | M32: Link | N32: AGRI-P0001 | O32: Received
A33: 32 | B33: 45439 | D33: Aero0029 | E33: Sidewall | F33: 1 | G33: Nextgen | H33: 6300 | I33: =F33*H33 -> 6300 | J33: =0.18*I33 -> 1134 | K33: 118 | L33: =SUM(I33:K33) -> 7552 | M33: Link | N33: AGRI-P0001 | O33: Received
A34: 33 | B34: 45440 | D34: - | E34: Calibration Testing(NABL certification) | F34: 1 | G34: Dynamic Calibration | H34: 0 | I34: =F34*H34 -> 0 | J34: =0.18*I34 -> 0 | K34: 0 | L34: =SUM(I34:K34) -> 0 | N34: AGRI-P0001 | O34: Received
A35: 34 | B35: 45440 | D35: Aero0186 | E35: =VLOOKUP(D35,'Component Master'!B16:D208,3,0) -> Tattu 22000mAh 6S Lipo Battery | F35: 4 | G35: Elecdrone Technologies | H35: 18000 | I35: =F35*H35 -> 72000 | J35: =0.18*I35 -> 12960 | K35: 0 | L35: =SUM(I35:K35) -> 84960 | M35: - | N35: AGRI-P0001 | O35: Received
A36: 35 | B36: 45440 | D36: - | E36: Portable Generator | F36: - | G36: - | H36: 0 | I36: 0 | J36: =0.18*I36 -> 0 | K36: 0 | L36: =SUM(I36:K36) -> 0 | M36: - | N36: AGRI-P0001 | O36: Yet to Place | Q36: Waiting for Tech team confirmation
A37: 36 | B37: 45444 | D37: Aero0027 | E37: =VLOOKUP(D37,'Component Master'!B17:D209,3,0) -> Alind water jet cutting | F37: 2 | G37: Alind | H37: 542 | I37: =F37*H37 -> 1084 | J37: =0.12*I37 -> 130.08 | K37: 0 | L37: =SUM(I37:K37) -> 1214.08 | N37: AGRI-P0001 | O37: Received
A38: 37 | B38: 45447 | D38: Aero0115 | E38: =VLOOKUP(D38,'Component Master'!B18:D210,3,0) -> 10L Tank | F38: 1 | G38: Elecdrone Technologies | H38: 6860 | I38: =F38*H38 -> 6860 | J38: =0.05*I38 -> 343 | K38: 0 | L38: =SUM(I38:K38) -> 7203 | N38: AGRI-P0001 | O38: Received
A39: 38 | B39: 45447 | D39: Aero0185 | E39: =VLOOKUP(D39,'Component Master'!B19:D211,3,0) -> QS8-S Anti spark Male/Female connector pair | F39: 6 | G39: Macfos | H39: 558.06 | I39: =F39*H39 -> 3348.36 | J39: =0.18*I39 -> 602.7048 | K39: 49 | L39: =SUM(I39:K39) -> 4000.0648 | N39: AGRI-P0001 | O39: Received
A40: 39 | B40: 45448 | D40: Aero0187 | E40: FrSky 900MHz Super 8 Antenna for R9M and R9M Lite Module_ FCC version | F40: 1 | G40: Macfos | H40: 1100.85 | I40: =F40*H40 -> 1100.85 | J40: =0.18*I40 -> 198.153 | K40: 0 | L40: =SUM(I40:K40) -> 1299.003 | N40: NANO | O40: Received | Q40: Online order/COD
A41: 40 | B41: 45448 | D41: Aero0188 | E41: Avatar VTX antenna (2 pcs ) | F41: 1 | G41: Macfos | H41: 1329.66 | I41: =F41*H41 -> 1329.66 | J41: =0.18*I41 -> 239.3388 | K41: 0 | L41: =SUM(I41:K41) -> 1568.9988 | N41: NANO | O41: Received | Q41: Online order/COD
A42: 41 | B42: 45448 | D42: Aero0187 | E42: FrSky 900MHz Super 8 Antenna for R9M and R9M Lite Module_ FCC version | F42: 1 | G42: Engineer store | H42: 1298 | I42: =F42*H42 -> 1298 | J42: =0.18*I42 -> 233.64 | K42: 75 | L42: =SUM(I42:K42) -> 1606.64 | N42: NANO | O42: Order cancelled | Q42: COD
A43: 42 | B43: 45448 | D43: Aero0190 | E43: Void stickers | F43: 200 | G43: Pio printers | H43: 4.16 | I43: =F43*H43 -> 832 | J43: =0.18*I43 -> 149.76 | K43: 0 | L43: =SUM(I43:K43) -> 981.76 | N43: ALL | O43: Received
A44: 43 | B44: 45448 | D44: Aero0191 | E44: Printing machine-Label Sticker | F44: 1 | G44: EPSON | H44: 15880 | I44: =F44*H44 -> 15880 | J44: =0.18*I44 -> 2858.4 | K44: 0 | L44: =SUM(I44:K44) -> 18738.4 | N44: INVENTORY | O44: Received
A45: 44 | B45: 45448 | D45: Aero0189 | E45: iBELL Rechargeable Weight Machine | F45: 2 | G45: Amazon | H45: 336.44 | I45: =F45*H45 -> 672.88 | J45: =0.18*I45 -> 121.1184 | K45: 0 | L45: =SUM(I45:K45) -> 793.9984 | N45: AGRI-P0001 | O45: Received
A46: 45 | B46: 45453 | D46: Aero0110 | E46: Nozzle | F46: 5 | G46: Elecdrone Technologies | H46: 840 | I46: =F46*H46 -> 4200 | J46: =0.05*I46 -> 210 | K46: 0 | L46: =SUM(I46:K46) -> 4410 | N46: AGRI-P0001 | O46: Received
A47: 46 | B47: 45453 | D47: Aero0110 | E47: Hose Pipe 6mm OD 4MM ID | F47: 5 | G47: Elecdrone Technologies | H47: 40 | I47: =F47*H47 -> 200 | J47: =0.18*I47 -> 36 | K47: 0 | L47: =SUM(I47:K47) -> 236 | N47: AGRI-P0001 | O47: Received
A48: 47 | B48: 45453 | D48: Aero0110 | E48: Hose Pipe 8mm OD 6MM ID | F48: 3 | G48: Elecdrone Technologies | H48: 54 | I48: =F48*H48 -> 162 | J48: =0.18*I48 -> 29.16 | K48: 0 | L48: =SUM(I48:K48) -> 191.16 | N48: AGRI-P0001 | O48: Received
A49: 48 | B49: 45453 | D49: Aero0110 | E49: Hose Pipe 10mm OD 8MM ID | F49: 2 | G49: Elecdrone Technologies | H49: 81 | I49: =F49*H49 -> 162 | J49: =0.18*I49 -> 29.16 | K49: 0 | L49: =SUM(I49:K49) -> 191.16 | N49: AGRI-P0001 | O49: Received
A50: 49 | B50: 45453 | D50: Aero0110 | E50: Hose Pipe 12mm OD 10MM ID | F50: 1 | G50: Elecdrone Technologies | H50: 90 | I50: =F50*H50 -> 90 | J50: =0.18*I50 -> 16.2 | K50: 0 | L50: =SUM(I50:K50) -> 106.2 | N50: AGRI-P0001 | O50: Received
A51: 50 | B51: 45453 | D51: Aero0185 | E51: =VLOOKUP(D51,'Component Master'!B31:D223,3,0) -> QS8-S Anti spark Male/Female connector pair | F51: 10 | G51: Macfos | H51: 669 | I51: =F51*H51 -> 6690 | J51: 0 | K51: =99+25 -> 124 | L51: =SUM(I51:K51) -> 6814 | N51: AGRI-P0001 | O51: Received
A52: 51 | B52: 45454 | D52: Aero0186 | E52: =VLOOKUP(D52,'Component Master'!B32:D224,3,0) -> Tattu 22000mAh 6S Lipo Battery | F52: 4 | G52: Elecdrone Technologies | H52: 18000 | I52: =F52*H52 -> 72000 | J52: =0.18*I52 -> 12960 | K52: 0 | L52: =SUM(I52:K52) -> 84960 | N52: AGRI-P0001 | O52: Received
A53: 52 | B53: 45458 | D53: Aero0192 | E53: Horizontal Landing gear | F53: 1 | G53: Elecdrone Technologies | H53: 1680 | I53: =F53*H53 -> 1680 | J53: =0.05*I53 -> 84 | K53: 0 | L53: =SUM(I53:K53) -> 1764 | N53: AGRI-P0001 | O53: Received
A54: 53 | B54: 45458 | D54: Aero0004 | E54: =VLOOKUP(D54,'Component Master'!B2:D226,3,0) -> Agri Carry case with Foam | F54: 2 | G54: Aerotek | H54: 17500 | I54: =F54*H54 -> 35000 | J54: =0.18*I54 -> 6300 | K54: 0 | L54: =SUM(I54:K54) -> 41300 | N54: AGRI-P0001 | O54: Received
A55: 54 | B55: 45460 | D55: Aero0193 | E55: UIN Plate | F55: 1 | G55: K Square Engineering | H55: 600 | I55: =F55*H55 -> 600 | J55: =0.18*I55 -> 108 | K55: 0 | L55: =SUM(I55:K55) -> 708 | N55: AGRI-P0001 | O55: Received
A56: 55 | B56: 45460 | D56: Aero0194 | E56: PU Hose Tube cutter | F56: 2 | G56: Amazon | H56: 249.15 | I56: =F56*H56 -> 498.3 | J56: =0.18*I56 -> 89.694 | K56: 0 | L56: =SUM(I56:K56) -> 587.994 | N56: AGRI-P0001 | O56: Received | Q56: Online order/COD
A57: 56 | B57: 45460 | D57: Aero0195 | E57: Servo cables-45cm | F57: 6 | G57: Macfos | H57: 66.95 | I57: =F57*H57 -> 401.7 | J57: =0.18*I57 -> 72.306 | K57: 0 | L57: =SUM(I57:K57) -> 474.006 | N57: AGRI-P0001 | O57: Received
A58: 57 | B58: 45460 | D58: Aero0196 | E58: Servo cables-60cm | F58: 6 | G58: Macfos | H58: 83.9 | I58: =F58*H58 -> 503.4 | J58: =0.18*I58 -> 90.612 | K58: 0 | L58: =SUM(I58:K58) -> 594.012 | N58: AGRI-P0001 | O58: Received
A59: 58 | B59: 45462 | D59: Aero0171 | E59: =VLOOKUP(D59,'Component Master'!B7:D231,3,0) -> CF Sheet 500*500mm*3mm | F59: 2 | G59: Think Robotics | H59: 12711.856 | I59: =F59*H59 -> 25423.712 | J59: =0.18*I59 -> 4576.2682 | K59: 0 | L59: =SUM(I59:K59) -> 29999.98 | N59: ALL | O59: Order Placed
A60: 59 | B60: 45462 | D60: Aero0009 | E60: =VLOOKUP(D60,'Component Master'!B8:D232,3,0) -> 300mm * 200mm * 2mm | F60: 4 | G60: Think Robotics | H60: 2711.856 | I60: =F60*H60 -> 10847.424 | J60: =0.18*I60 -> 1952.5363 | K60: 0 | L60: =SUM(I60:K60) -> 12799.96 | N60: ALL | O60: Order Placed
A61: 60 | B61: 45464 | D61: Aero0197 | E61: =VLOOKUP(D61,'Component Master'!B9:D233,3,0) -> Sensor mounting plate | F61: 2 | G61: Nextgen | H61: 1500 | I61: =F61*H61 -> 3000 | J61: =0.18*I61 -> 540 | K61: 0 | L61: =SUM(I61:K61) -> 3540 | N61: AGRI-P0001 | O61: Received
A62: 61 | B62: 45464 | D62: Aero0098 | E62: =VLOOKUP(D62,'Component Master'!B10:D234,3,0) -> Obstacle Avoidance Sensor | F62: 1 | G62: Macfos | H62: 27576 | I62: =F62*H62 -> 27576 | J62: =0.18*I62 -> 4963.68 | K62: 0 | L62: =SUM(I62:K62) -> 32539.68 | N62: AGRI-P0001 | O62: Received | Q62: Sensor for PDRL Testing
A63: 62 | B63: 45464 | D63: Aero0029 | E63: Tolerance Plate | F63: 1 | G63: Nextgen | H63: 1500 | I63: =F63*H63 -> 1500 | J63: =0.18*I63 -> 270 | K63: 0 | L63: =SUM(I63:K63) -> 1770 | N63: AGRI-P0001 | O63: Received
A64: 63 | B64: 45465 | D64: Aero0029 | E64: Lug connector enclosing plate | F64: 2 | G64: AMUSE | H64: 296.7 | I64: 593.4 | J64: 106.812 | K64: 0 | L64: 700.212 | N64: AGRI-TC | O64: Received
A65: 64 | B65: 45465 | D65: Aero0029 | E65: PCB Enclosure | F65: 2 | G65: AMUSE | H65: 2614.4 | I65: 5228.8 | J65: 941.184 | K65: 0 | L65: 6169.984 | N65: AGRI-TC | O65: Received
A66: 65 | B66: 45465 | D66: Aero0183 | E66: 1/8 inch water flow sensor-YF-S401 | F66: 2 | G66: ZBOTICS | H66: 181 | I66: 362 | J66: 65.16 | K66: 120.36 | L66: 547.52 | N66: AGRI-TC | O66: Received
A67: 66 | B67: 45465 | D67: Aero0198 | E67: Amass XT150 Gold plated Male/Female connector with High current(130A Max) | F67: 4 | G67: MACFOS LIMITED | H67: 111.1025 | I67: 444.41 | J67: 79.9938 | K67: 113 | L67: 637.4038 | N67: AGRI-TC | O67: Received
A68: 67 | B68: 45465 | D68: Aero0199 | E68: Amass AS150 Anti spark Insulating Gold plated connector 1 pair | F68: 4 | G68: MACFOS LIMITED | H68: 465.255 | I68: 1861.02 | J68: 334.9836 | K68: 113 | L68: 2309.0036 | N68: AGRI-TC | O68: Received
A69: 68 | B69: 45465 | D69: Aero0031 | E69: MK15 Remote controller | F69: 2 | G69: Elecdrone Technologies | H69: 39400 | I69: 78800 | J69: 14184 | K69: 0 | L69: 92984 | N69: AGRI-TC | O69: Received
A70: 69 | B70: 45465 | D70: Aero0170 | E70: E610P frame with Tank | F70: 2 | G70: Elecdrone Technologies | H70: 42600 | I70: 85200 | J70: 4260 | K70: 0 | L70: 89460 | N70: AGRI-TC | O70: Received
A71: 70 | B71: 45465 | D71: Aero0186 | E71: Tattu 6S 22000 mAh battery | F71: 4 | G71: Elecdrone Technologies | H71: 17700 | I71: 70800 | J71: 12744 | K71: 0 | L71: 83544 | N71: AGRI-TC | O71: Received
A72: 71 | B72: 45465 | D72: Aero0064 | E72: Hobbywing X6 Plus 150KV motor CW combo | F72: 6 | G72: Elecdrone Technologies | H72: 10520 | I72: 63120 | J72: 3156 | K72: 0 | L72: 66276 | N72: AGRI-TC | O72: Received
A73: 72 | B73: 45465 | D73: Aero0064 | E73: Hobbywing X6 Plus 150KV motor CW combo | F73: 6 | G73: Elecdrone Technologies | H73: 10520 | I73: 63120 | J73: 3156 | K73: 0 | L73: 66276 | N73: AGRI-TC | O73: Received
A74: 73 | B74: 45465 | D74: Aero0057 | E74: SKYRC 1080W charger | F74: 2 | G74: Elecdrone Technologies | H74: 17000 | I74: 34000 | J74: 6120 | K74: 0 | L74: 40120 | N74: AGRI-TC | O74: Received
A75: 74 | B75: 45465 | D75: Aero0110 | E75: Hobbywing 5LPM sprayer kit | F75: 2 | G75: Elecdrone Technologies | H75: 10200 | I75: 20400 | J75: 1020 | K75: 0 | L75: 21420 | N75: AGRI-TC | O75: Received
... A101: 100 | B101: 45465 | D101: Aero0197 | E101: Sensor mounting plate | F101: 2 | G101: Nextgen | H101: 1500 | I101: 3000 | J101: 576 | K101: 200 | L101: 3776 | N101: P0001 | O101: Received
A102: 101 | B102: 45465 | D102: Aero0028 | E102: Canopy | F102: 2 | G102: Nextgen | H102: 21920 | I102: =H102*F102 -> 43840 | J102: =0.18*I102 -> 7891.2 | K102: 150 | L102: =I102+J102+K102 -> 51881.2 | N102: AGRI-TC | O102: Received
A103: 102 | B103: 45465 | D103: Aero0029 | E103: Sidewall | F103: 2 | G103: Nextgen | H103: 6300 | I103: =H103*F103 -> 12600 | J103: =0.18*I103 -> 2268 | K103: 150 | L103: =I103+J103+K103 -> 15018 | N103: AGRI-TC | O103: Received
A104: 103 | B104: 45465 | D104: Aero0004 | E104: Agri Carry case | F104: 2 | G104: Aerotek | H104: 17500 | I104: =H104*F104 -> 35000 | J104: =0.18*I104 -> 6300 | K104: 0 | L104: =I104+J104+K104 -> 41300 | N104: AGRI-TC | O104: Received
A105: 104 | B105: 45468 | D105: - | E105: Bricks | F105: 30 | G105: Local | H105: 12 | I105: =H105*F105 -> 360 | J105: 0 | K105: 0 | L105: =I105+J105+K105 -> 360 | N105: ALL | O105: Received
A106: 105 | B106: 45469 | D106: Aero0201 | E106: Crimping tool | F106: 1 | G106: Flipkart | H106: 444 | I106: =H106*F106 -> 444 | J106: 0 | K106: 0 | L106: =I106+J106+K106 -> 444 | N106: ALL | O106: Received
A107: 106 | B107: 45469 | D107: - | E107: 50KG CI weight | F107: 2 | G107: Venkateswara weighing services | H107: 4300 | I107: 8600 | J107: 1548 | K107: 0 | L107: 10148 | N107: ALL | O107: Received
A108: 107 | B108: 45469 | D108: - | E108: 20KG CI weight | F108: 4 | G108: Venkateswara weighing services | H108: 1600 | I108: 6400 | J108: 1152 | K108: 0 | L108: 7552 | N108: ALL | O108: Received
A109: 108 | B109: 45471 | D109: Aero0201 | E109: Crimping tool | F109: 1 | G109: Amazon | H109: 4009.82 | I109: =H109*F109 -> 4009.82 | J109: =0.12*I109 -> 481.1784 | K109: 0 | L109: =I109+J109+K109 -> 4490.9984 | N109: ALL | O109: Received
A110: 109 | B110: 45472 | D110: Aero0203 | E110: Brass Insert-OD 4.8mm(Pack of 25) | F110: 4 | G110: Macfos | H110: 58.47 | I110: =H110*F110 -> 233.88 | J110: =0.18*I110 -> 42.0984 | K110: 0 | L110: =I110+J110+K110 -> 275.9784 | N110: AGRI-TC | O110: Received
A111: 110 | B111: 45472 | D111: Aero0175 | E111: High Quality Ultra Flexible 8AWG Silicon Wire 1m (Black) | F111: 5 | G111: Elecdrone Technologies | H111: 370 | I111: =H111*F111 -> 1850 | J111: =0.18*I111 -> 333 | K111: 0 | L111: =I111+J111+K111 -> 2183 | N111: ALL | O111: Received
A112: 111 | B112: 45472 | D112: Aero0175 | E112: High Quality Ultra Flexible 8AWG Silicon Wire 1m (Red) | F112: 5 | G112: Elecdrone Technologies | H112: 370 | I112: =H112*F112 -> 1850 | J112: =0.18*I112 -> 333 | K112: 0 | L112: =I112+J112+K112 -> 2183 | N112: ALL | O112: Received
A113: 112 | B113: 45472 | D113: Aero0202 | E113: Telemetry cable | F113: 5 | G113: Elecdrone Technologies | H113: 385 | I113: =H113*F113 -> 1925 | J113: =0.18*I113 -> 346.5 | K113: 0 | L113: =I113+J113+K113 -> 2271.5 | N113: ALL | O113: Received
A114: 113 | B114: 45474 | D114: Aero0204 | E114: Laser engraving on UIN plate | F114: 3 | G114: RC Laser tech | H114: 75 | I114: =H114*F114 -> 225 | J114: =0.18*I114 -> 40.5 | K114: 0 | L114: =I114+J114+K114 -> 265.5 | N114: P0001 | O114: Received
A115: 114 | B115: 45474 | D115: Aero0193 | E115: UIN Plate | F115: 2 | G115: K Square Engineering | H115: 350 | I115: =H115*F115 -> 700 | J115: =0.18*I115 -> 126 | K115: 0 | L115: =I115+J115+K115 -> 826 | N115: P0001 | O115: Received
A116: 115 | B116: 45477 | D116: Aero0205 | E116: Weighing scale-100Kg | F116: 1 | G116: Venkateswara weighing services | H116: 6900 | I116: =H116*F116 -> 6900 | J116: =0.18*I116 -> 1242 | K116: 0 | L116: =I116+J116+K116 -> 8142 | N116: ALL | O116: Received
A117: 116 | B117: 45478 | D117: Aero0027 | E117: 2mm Plate 01-Water jet cutting | F117: 1 | G117: Alind | H117: 1081 | I117: =H117*F117 -> 1081 | J117: =0.12*I117 -> 129.72 | K117: 0 | L117: =I117+J117+K117 -> 1210.72 | N117: P0002 | O117: Received
A118: 117 | B118: 45478 | D118: Aero0027 | E118: 2mm Plate 02- Water jet cutting | F118: 1 | G118: Alind | H118: 1650 | I118: =H118*F118 -> 1650 | J118: =0.12*I118 -> 198 | K118: 0 | L118: =I118+J118+K118 -> 1848 | N118: P0002 | O118: Received
A119: 118 | B119: 45478 | D119: Aero0027 | E119: 3mm Plate 01- Water jet cutting | F119: 1 | G119: Alind | H119: 1281 | I119: =H119*F119 -> 1281 | J119: =0.12*I119 -> 153.72 | K119: 0 | L119: =I119+J119+K119 -> 1434.72 | N119: P0002 | O119: Received
A120: 119 | B120: 45478 | D120: Aero0206 | E120: Square Flange Linear Bearing | F120: 4 | G120: Robokits | H120: 102 | I120: =H120*F120 -> 408 | J120: =0.18*I120 -> 73.44 | K120: 0 | L120: =I120+J120+K120 -> 481.44 | N120: P0002 | O120: Received
A121: 120 | B121: 45478 | D121: Aero0029 | E121: L MOUNT for skid-3D Printed parts | F121: 4 | G121: Amuse | H121: 820 | I121: =H121*F121 -> 3280 | J121: =0.18*I121 -> 590.4 | K121: 0 | L121: =I121+J121+K121 -> 3870.4 | N121: P0002 | O121: Received
A122: 121 | B122: 45478 | D122: Aero0029 | E122: Sensor mount bottom-3D printed parts | F122: 1 | G122: Amuse | H122: 1750.7 | I122: =H122*F122 -> 1750.7 | J122: =0.18*I122 -> 315.126 | K122: 0 | L122: =I122+J122+K122 -> 2065.826 | N122: P0002 | O122: Received
A123: 122 | B123: 45478 | D123: Aero0029 | E123: sensor mount top-3D printed parts | F123: 1 | G123: Amuse | H123: 1980.3 | I123: =H123*F123 -> 1980.3 | J123: =0.18*I123 -> 356.454 | K123: 0 | L123: =I123+J123+K123 -> 2336.754 | N123: P0002 | O123: Received
A124: 123 | B124: 45478 | D124: Aero0029 | E124: Skid T Joint-3D printed parts | F124: 4 | G124: Amuse | H124: 422.3 | I124: =H124*F124 -> 1689.2 | J124: =0.18*I124 -> 304.056 | K124: 0 | L124: =I124+J124+K124 -> 1993.256 | N124: P0002 | O124: Received
A125: 124 | B125: 45478 | D125: Aero0029 | E125: Damper Connector | F125: 6 | G125: Nextgen | H125: 795 | I125: =H125*F125 -> 4770 | J125: =0.18*I125 -> 858.6 | K125: 0 | L125: =I125+J125+K125 -> 5628.6 | N125: P0002 | O125: Received
...

Sheet Inward
A1: Date | B1: CID/SKU Number | C1: Specification | D1: Qty | E1: Vendor | F1: Invoice Date | G1: Unit Price | H1: Subtotal | I1: GST | J1: Shipping | K1: Total Price | L1: Project
A2: 45414 | B2: Aero0092 | C2: =VLOOKUP(B2,'Component Master'!B:D,3,0) -> Here3+ | D2: 3 | E2: Vyom Drones | F2: 45411 | G2: 20000 | H2: =G2*D2 -> 60000 | I2: =0.05*H2 -> 3000 | J2: 0 | K2: =H2+I2+J2 -> 63000 | L2: P0002
A3: 45414 | B3: Aero0162 | C3: =VLOOKUP(B3,'Component Master'!B:D,3,0) -> 400mm*380mm*3mm | D3: 4 | E3: Hindustan Engineers | F3: 45414 | G3: 4907 | H3: =G3*D3 -> 19628 | I3: =0.05*H3 -> 981.4 | J3: 0 | K3: =H3+I3+J3 -> 20609.4 | L3: P0001
A4: 45416 | B4: Aero0163 | C4: =VLOOKUP(B4,'Component Master'!B:D,3,0) -> 3.5mm Male Female Banana Plug Bullet Connector (Pack of 10) | D4: 2 | E4: Robocraze | F4: 45411 | G4: 217 | H4: =G4*D4 -> 434 | I4: 0 | J4: 100 | K4: =H4+I4+J4 -> 534 | L4: P0002
A5: 45416 | B5: Aero0164 | C5: =VLOOKUP(B5,'Component Master'!B:D,3,0) -> Amass XT90E-M male connector | D5: 1 | E5: Flyrobo | F5: 45413 | G5: 83.9 | H5: =G5*D5 -> 83.9 | I5: =0.18*H5 -> 15.102 | J5: 79 | K5: =H5+I5+J5 -> 178.002 | L5: P0002
A6: 45418 | B6: Aero0066 | C6: =VLOOKUP(B6,'Component Master'!B:D,3,0) -> Air 40 Amps | D6: 8 | E6: Vyom Drones | F6: 45414 | G6: 2800 | H6: =G6*D6 -> 22400 | I6: =0.05*H6 -> 1120 | J6: 0 | K6: =H6+I6+J6 -> 23520 | L6: P0002
A7: 45418 | B7: Aero0087 | C7: =VLOOKUP(B7,'Component Master'!B:D,3,0) -> PIXHAWK_CUBE Orange+ with ADSB Set | D7: 3 | E7: Vyom Drones | F7: 45415 | G7: 30000 | H7: =G7*D7 -> 90000 | I7: =0.05*G7 -> 1500 | J7: 0 | K7: =H7+I7+J7 -> 91500 | L7: P0001& P0002
A8: 45419 | B8: Aero0027 | C8: =VLOOKUP(B8,'Component Master'!B:D,3,0) -> Alind water jet cutting | D8: 1 | E8: Alind | F8: 45419 | G8: 1013 | H8: =G8*D8 -> 1013 | I8: =0.12*H8 -> 121.56 | J8: 0 | K8: =H8+I8+J8 -> 1134.56 | L8: P0001
A9: 45419 | B9: Aero0027 | C9: =VLOOKUP(B9,'Component Master'!B:D,3,0) -> Alind water jet cutting | D9: 4 | E9: Alind | F9: 45419 | G9: 1052 | H9: =G9*D9 -> 4208 | I9: =0.12*H9 -> 504.96 | J9: 0 | K9: =H9+I9+J9 -> 4712.96 | L9: P0001
A10: 45419 | B10: Aero0027 | C10: =VLOOKUP(B10,'Component Master'!B:D,3,0) -> Alind water jet cutting | D10: 4 | E10: Alind | F10: 45419 | G10: 1048 | H10: =G10*D10 -> 4192 | I10: =0.12*H10 -> 503.04 | J10: 0 | K10: =H10+I10+J10 -> 4695.04 | L10: P0001
A11: 45419 | B11: Aero0027 | C11: =VLOOKUP(B11,'Component Master'!B:D,3,0) -> Alind water jet cutting | D11: 8 | E11: Alind | F11: 45419 | G11: 1632 | H11: =G11*D11 -> 13056 | I11: =0.12*H11 -> 1566.72 | J11: 0 | K11: =H11+I11+J11 -> 14622.72 | L11: P0001
A12: 45419 | B12: Aero0027 | C12: =VLOOKUP(B12,'Component Master'!B:D,3,0) -> Alind water jet cutting | D12: 1 | E12: Alind | F12: 45419 | G12: 896 | H12: =G12*D12 -> 896 | I12: =0.12*H12 -> 107.52 | J12: 0 | K12: =H12+I12+J12 -> 1003.52 | L12: P0001
A13: 45421 | B13: Aero0178 | C13: =VLOOKUP(B13,'Component Master'!B:D,3,0) -> Hobbywing X6 Pro motor CW | D13: 3 | E13: Elecdrones Technologies | F13: 45421 | G13: 13900 | H13: =G13*D13 -> 41700 | I13: =0.05*H13 -> 2085 | J13: 0 | K13: =H13+I13+J13 -> 43785 | L13: P0003
A14: 45421 | B14: Aero0179 | C14: =VLOOKUP(B14,'Component Master'!B:D,3,0) -> Hobbywing X6 Pro motor CCW | D14: 3 | E14: Elecdrones Technologies | F14: 45421 | G14: 13900 | H14: =G14*D14 -> 41700 | I14: =0.05*H14 -> 2085 | J14: 0 | K14: =H14+I14+J14 -> 43785 | L14: P0003
A15: 45421 | B15: Aero0165 | C15: =VLOOKUP(B15,'Component Master'!B:D,3,0) -> 2388 inch Propellers | D15: 9 | E15: Elecdrones Technologies | F15: 45421 | G15: 1413 | H15: =G15*D15 -> 12717 | I15: =0.05*H15 -> 635.85 | J15: 0 | K15: =H15+I15+J15 -> 13352.85 | L15: P0003
A16: 45421 | B16: Aero0180 | C16: =VLOOKUP(B16,'Component Master'!B:D,3,0) -> GPS Stand-Agri | D16: 1 | E16: Elecdrones Technologies | F16: 45421 | G16: 388 | H16: =G16*D16 -> 388 | I16: =0.05*H16 -> 19.4 | J16: 0 | K16: =H16+I16+J16 -> 407.4 | L16: P0001
A17: 45422 | B17: Aero0152 | C17: =VLOOKUP(B17,'Component Master'!B:D,3,0) -> Flysky FS-i6S 2.4GHz 10CH AFHDS 2A RC Transmitter With FS-iA10B 10CH Receiver | D17: 1 | E17: Macfos | F17: 45420 | G17: 4809.52 | H17: =G17*D17 -> 4809.52 | I17: =0.05*H17 -> 240.476 | J17: 40.57 | K17: =H17+I17+J17 -> 5090.566 | L17: P0003
A18: 45422 | B18: Aero0173 | C18: =VLOOKUP(B18,'Component Master'!B:D,3,0) -> Hall Sensor | D18: 1 | E18: Macfos | F18: 45420 | G18: 25571.43 | H18: =G18*D18 -> 25571.43 | I18: =0.05*H18 -> 1278.5715 | J18: 40.57 | K18: =H18+I18+J18 -> 26890.571 | L18: P0003
A19: 45422 | B19: Aero0020 | C19: =VLOOKUP(B19,'Component Master'!B:D,3,0) -> Pixhawk Dampner plate | D19: 4 | E19: Macfos | F19: 45420 | G19: 148.305 | H19: =G19*D19 -> 593.22 | I19: =0.18*H19 -> 106.7796 | J19: 40.57 | K19: =H19+I19+J19 -> 740.5696 | L19: P0003
A20: 45422 | B20: Aero0175 | C20: =VLOOKUP(B20,'Component Master'!B:D,3,0) -> High Quality Ultra Flexible 8AWG Silicon Wire 2m (Black) | D20: 2 | E20: Macfos | F20: 45420 | G20: 555.085 | H20: =G20*D20 -> 1110.17 | I20: =0.18*H20 -> 199.8306 | J20: 40.57 | K20: =H20+I20+J20 -> 1350.5706 | L20: P0003
A21: 45422 | B21: Aero0176 | C21: =VLOOKUP(B21,'Component Master'!B:D,3,0) -> Amass XT60-U Female Bullet Connector | D21: 10 | E21: Macfos | F21: 45420 | G21: 29.661 | H21: =G21*D21 -> 296.61 | I21: =0.18*H21 -> 53.3898 | J21: 40.57 | K21: =H21+I21+J21 -> 390.5698 | L21: P0003
A22: 45422 | B22: Aero0177 | C22: =VLOOKUP(B22,'Component Master'!B:D,3,0) -> Amass XT60-U Male Bullet Connector | D22: 10 | E22: Macfos | F22: 45420 | G22: 29.661 | H22: =G22*D22 -> 296.61 | I22: =0.18*H22 -> 53.3898 | J22: 40.57 | K22: =H22+I22+J22 -> 390.5698 | L22: P0003
A23: 45422 | B23: Aero0171 | C23: =VLOOKUP(B23,'Component Master'!B:D,3,0) -> CF Sheet 500*500mm*3mm | D23: 2 | E23: Macfos | F23: 45420 | G23: 7428.815 | H23: =G23*D23 -> 14857.63 | I23: =0.18*H23 -> 2674.3734 | J23: 40.57 | K23: =H23+I23+J23 -> 17572.573 | L23: P0003
A24: 45426 | B24: Aero0029 | C24: =VLOOKUP(B24,'Component Master'!B:D,3,0) -> 3D Printed Parts | D24: 2 | E24: Amuse | F24: 45425 | G24: 282.9 | H24: =G24*D24 -> 565.8 | I24: =0.18*H24 -> 101.844 | J24: 0 | K24: =H24+I24+J24 -> 667.644 | L24: P0001
A25: 45426 | B25: Aero0029 | C25: =VLOOKUP(B25,'Component Master'!B:D,3,0) -> 3D Printed Parts | D25: 2 | E25: Amuse | F25: 45425 | G25: 2492.8 | H25: =G25*D25 -> 4985.6 | I25: =0.18*H25 -> 897.408 | J25: 0 | K25: =H25+I25+J25 -> 5883.008 | L25: P0001
A26: 45428 | B26: Aero0029 | C26: =VLOOKUP(B26,'Component Master'!B:D,3,0) -> 3D Printed Parts | D26: 1 | E26: Nextgen | F26: 45428 | G26: 21750 | H26: =G26*D26 -> 21750 | I26: =0.18*H26 -> 3915 | J26: 118 | K26: =H26+I26+J26 -> 25783 | L26: P0001
A27: 45428 | B27: Aero0029 | C27: =VLOOKUP(B27,'Component Master'!B:D,3,0) -> 3D Printed Parts | D27: 1 | E27: Nextgen | F27: 45428 | G27: 6300 | H27: 6300 | I27: =0.18*H27 -> 1134 | J27: 118 | K27: =H27+I27+J27 -> 7552 | L27: P0001
A28: 45429 | B28: Aero0173 | C28: =VLOOKUP(B28,'Component Master'!B:D,3,0) -> Hall Sensor | D28: 3 | E28: Vyom Drones | F28: 45426 | G28: 4420 | H28: =G28*D28 -> 13260 | I28: =0.05*H28 -> 663 | J28: 0 | K28: =H28+I28+J28 -> 13923 | L28: P0001
A29: 45429 | B29: Aero0183 | C29: =VLOOKUP(B29,'Component Master'!B:D,3,0) -> Water flow sensor-White | D29: 2 | E29: Macfos | F29: 45427 | G29: 189.83 | H29: =G29*D29 -> 379.66 | I29: =0.18*H29 -> 68.3388 | J29: 74 | K29: =H29+I29+J29 -> 521.9988 | L29: P0001
A30: 45430 | B30: Aero0181 | C30: =VLOOKUP(B30,'Component Master'!B:D,3,0) -> Mauch 084: 4-14S BEC | D30: 2 | E30: Vyom Drones | F30: 45427 | G30: 3900 | H30: =G30*D30 -> 7800 | I30: =0.05*H30 -> 390 | J30: 0 | K30: =H30+I30+J30 -> 8190 | L30: P0001
A31: 45430 | B31: Aero0182 | C31: =VLOOKUP(B31,'Component Master'!B:D,3,0) -> Mauch 086: Adapter cable for Pixhawk 2 | D31: 2 | E31: Vyom Drones | F31: 45427 | G31: 500 | H31: =G31*D31 -> 1000 | I31: =0.05*H31 -> 50 | J31: 0 | K31: =H31+I31+J31 -> 1050 | L31: P0001
A32: 45432 | B32: Aero0162 | C32: =VLOOKUP(B32,'Component Master'!B:D,3,0) -> 400mm*380mm*3mm | D32: 2 | E32: Hindustan Engineers | F32: 45430 | G32: 4907 | H32: =G32*D32 -> 9814 | I32: =0.18*H32 -> 1766.52 | J32: 0 | K32: =H32+I32+J32 -> 11580.52 | L32: P0001
A33: 45433 | B33: Aero0170 | C33: =VLOOKUP(B33,'Component Master'!B:D,3,0) -> EFT E610P Airframe with 10L Tank | D33: 1 | E33: Macfos | F33: 45427 | G33: 38903.81 | H33: =G33*D33 -> 38903.81 | I33: =0.05*H33 -> 1945.1905 | J33: 600 | K33: =H33+I33+J33 -> 41449.001 | L33: P0001
A34: 45433 | B34: Aero0171 | C34: =VLOOKUP(B34,'Component Master'!B:D,3,0) -> CF Sheet 500*500mm*3mm | D34: 2 | E34: Macfos | F34: 45427 | G34: 7316.95 | H34: =G34*D34 -> 14633.9 | I34: =0.18*H34 -> 2634.102 | J34: 600 | K34: =H34+I34+J34 -> 17868.002 | L34: P0001
A35: 45434 | B35: Aero0027 | C35: =VLOOKUP(B35,'Component Master'!B:D,3,0) -> Alind water jet cutting | D35: 2 | E35: Alind | F35: 45434 | G35: 1079 | H35: =G35*D35 -> 2158 | I35: =0.12*H35 -> 258.96 | J35: 0 | K35: =H35+I35+J35 -> 2416.96 | L35: P0001
A36: 45434 | B36: Aero0027 | C36: =VLOOKUP(B36,'Component Master'!B:D,3,0) -> Alind water jet cutting | D36: 2 | E36: Alind | F36: 45434 | G36: 1100 | H36: =G36*D36 -> 2200 | I36: =0.12*H36 -> 264 | J36: 0 | K36: =H36+I36+J36 -> 2464 | L36: P0001
A37: 45435 | B37: Aero0172 | C37: =VLOOKUP(B37,'Component Master'!B:D,3,0) -> Aluminium mount | D37: 12 | E37: Aerotek | F37: 45435 | G37: 2750 | H37: =G37*D37 -> 33000 | I37: 6048 | J37: 600 | K37: =H37+I37+J37 -> 39648 | L37: P0001
A38: 45436 | B38: Aero0027 | C38: =VLOOKUP(B38,'Component Master'!B:D,3,0) -> Alind water jet cutting | D38: 1 | E38: Alind | F38: 45436 | G38: 1100 | H38: =G38*D38 -> 1100 | I38: =0.12*H38 -> 132 | J38: 0 | K38: =H38+I38+J38 -> 1232 | L38: P0001
A39: 45439 | B39: Aero0029 | C39: =VLOOKUP(B39,'Component Master'!B:D,3,0) -> 3D Printed Parts | D39: 1 | E39: Monotech | F39: 45439 | G39: 16425 | H39: =G39*D39 -> 16425 | I39: =0.18*H39 -> 2956.5 | J39: 0 | K39: =H39+I39+J39 -> 19381.5 | L39: P0001
A40: 45439 | B40: Aero0184 | C40: =VLOOKUP(B40,'Component Master'!B:D,3,0) -> Liquid water Level sensor | D40: 3 | E40: Macfos | F40: 45436 | G40: 508.47 | H40: =G40*D40 -> 1525.41 | I40: =0.18*H40 -> 274.5738 | J40: 62 | K40: =H40+I40+J40 -> 1861.9838 | L40: P0001
A41: 45439 | B41: Aero0183 | C41: =VLOOKUP(B41,'Component Master'!B:D,3,0) -> Water flow sensor-White | D41: 1 | E41: Macfos | F41: 45436 | G41: 189.83 | H41: =G41*D41 -> 189.83 | I41: =0.18*H41 -> 34.1694 | J41: 62 | K41: =H41+I41+J41 -> 285.9994 | L41: P0001
A42: 45439 | B42: Aero0185 | C42: =VLOOKUP(B42,'Component Master'!B:D,3,0) -> QS8-S Anti spark Male/Female connector pair | D42: 2 | E42: Macfos | F42: 45436 | G42: 566.95 | H42: =G42*D42 -> 1133.9 | I42: =0.18*H42 -> 204.102 | J42: 25 | K42: =H42+I42+J42 -> 1363.002 | L42: P0001
A43: 45439 | B43: Aero0029 | C43: =VLOOKUP(B43,'Component Master'!B:D,3,0) -> 3D Printed Parts | D43: 2 | E43: Amuse | F43: 45439 | G43: 425.7 | H43: =G43*D43 -> 851.4 | I43: =0.18*H43 -> 153.252 | J43: 225 | K43: =H43+I43+J43 -> 1229.652 | L43: P0001
A44: 45439 | B44: Aero0029 | C44: =VLOOKUP(B44,'Component Master'!B:D,3,0) -> 3D Printed Parts | D44: 2 | E44: Amuse | F44: 45439 | G44: 395.6 | H44: =G44*D44 -> 791.2 | I44: =0.18*H44 -> 142.416 | J44: 225 | K44: =H44+I44+J44 -> 1158.616 | L44: P0001
A45: 45443 | B45: Aero0169 | C45: Data Acquistion System | D45: 2 | E45: APICO | F45: 45435 | G45: 38000 | H45: =G45*D45 -> 76000 | I45: =0.18*H45 -> 13680 | J45: 0 | K45: =H45+I45+J45 -> 89680 | L45: P0001
A46: 45444 | B46: Aero0027 | C46: =VLOOKUP(B46,'Component Master'!B:D,3,0) -> Alind water jet cutting | D46: 2 | E46: ALIND | F46: 45444 | G46: 542 | H46: =G46*D46 -> 1084 | I46: =0.18*H46 -> 195.12 | J46: 0 | K46: =H46+I46+J46 -> 1279.12 | L46: P0001
A47: 45447 | B47: Aero0115 | C47: =VLOOKUP(B47,'Component Master'!B:D,3,0) -> 10L Tank | D47: 1 | E47: Elecdrones Technologies | F47: 45448 | G47: 6860 | H47: =G47*D47 -> 6860 | I47: =0.18*H47 -> 1234.8 | J47: 0 | K47: =H47+I47+J47 -> 8094.8 | L47: P0001
A48: 45447 | B48: Aero0185 | C48: =VLOOKUP(B48,'Component Master'!B:D,3,0) -> QS8-S Anti spark Male/Female connector pair | D48: 6 | E48: Macfos | F48: 45448 | G48: 558.06833 | H48: =G48*D48 -> 3348.41 | I48: =0.18*H48 -> 602.7138 | J48: 49 | K48: =H48+I48+J48 -> 4000.1238 | L48: P0001
A49: 45453 | B49: Aero0187 | C49: =VLOOKUP(B49,'Component Master'!B:D,3,0) -> FrSky 900MHz Super 8 Antenna for R9M and R9M Lite Module_ FCC version | D49: 1 | E49: Macfos | F49: 45449 | G49: 1100.85 | H49: =G49*D49 -> 1100.85 | I49: =0.18*H49 -> 198.153 | J49: 0 | K49: =H49+I49+J49 -> 1299.003 | L49: P0001
A50: 45453 | B50: Aero0188 | C50: =VLOOKUP(B50,'Component Master'!B:D,3,0) -> Avatar VTX antenna (2 pcs ) | D50: 1 | E50: Macfos | F50: 45449 | G50: 1329.66 | H50: =G50*D50 -> 1329.66 | I50: =0.18*H50 -> 239.3388 | J50: 0 | K50: =H50+I50+J50 -> 1568.9988 | L50: P0001
A51: 45453 | B51: Aero0189 | C51: =VLOOKUP(B51,'Component Master'!B:D,3,0) -> iBELL Rechargeable Weight Machine | D51: 2 | E51: Amazon | F51: 45449 | G51: 336.44 | H51: =G51*D51 -> 672.88 | I51: =0.18*H51 -> 121.1184 | J51: 0 | K51: =H51+I51+J51 -> 793.9984 | L51: Inventory
A52: 45454 | B52: Aero0110 | C52: Nozzle | D52: 5 | E52: Elecdrone Technologies | F52: 45454 | G52: 840 | H52: =G52*D52 -> 4200 | I52: =0.05*H52 -> 210 | J52: 0 | K52: =SUM(H52:J52) -> 4410 | L52: P0001
A53: 45454 | B53: Aero0110 | C53: Hose Pipe 6mm OD 4MM ID | D53: 5 | E53: Elecdrone Technologies | F53: 45454 | G53: 40 | H53: =G53*D53 -> 200 | I53: =0.18*H53 -> 36 | J53: 0 | K53: =SUM(H53:J53) -> 236 | L53: P0001
A54: 45454 | B54: Aero0110 | C54: Hose Pipe 8mm OD 6MM ID | D54: 3 | E54: Elecdrone Technologies | F54: 45454 | G54: 54 | H54: =G54*D54 -> 162 | I54: =0.18*H54 -> 29.16 | J54: 0 | K54: =SUM(H54:J54) -> 191.16 | L54: P0001
A55: 45454 | B55: Aero0110 | C55: Hose Pipe 10mm OD 8MM ID | D55: 2 | E55: Elecdrone Technologies | F55: 45454 | G55: 81 | H55: =G55*D55 -> 162 | I55: =0.18*H55 -> 29.16 | J55: 0 | K55: =SUM(H55:J55) -> 191.16 | L55: P0001
A56: 45454 | B56: Aero0110 | C56: Hose Pipe 12mm OD 10MM ID | D56: 1 | E56: Elecdrone Technologies | F56: 45454 | G56: 90 | H56: =G56*D56 -> 90 | I56: =0.18*H56 -> 16.2 | J56: 0 | K56: =SUM(H56:J56) -> 106.2 | L56: P0001
A57: 45455 | B57: Aero0186 | C57: =VLOOKUP(B57,'Component Master'!B:D,3,0) -> Tattu 22000mAh 6S Lipo Battery | D57: 4 | E57: Elecdrone Technologies | F57: 45455 | G57: 18000 | H57: =G57*D57 -> 72000 | I57: =0.18*H57 -> 12960 | J57: 0 | K57: =SUM(H57:J57) -> 84960 | L57: P0001
A58: 45456 | B58: Aero0185 | C58: =VLOOKUP(B58,'Component Master'!B:D,3,0) -> QS8-S Anti spark Male/Female connector pair | D58: 10 | E58: Macfos | F58: 45454 | G58: 669 | H58: =G58*D58 -> 6690 | I58: =0.18*H58 -> 1204.2 | J58: 0 | K58: =SUM(H58:J58) -> 7894.2 | L58: P0001
A59: 45458 | B59: Aero0192 | C59: Horizontal Landing gear | D59: 1 | E59: Elecdrone Technologies | F59: 45458 | G59: 1680 | H59: =D59*G59 -> 1680 | I59: =0.05*H59 -> 84 | J59: 0 | K59: =SUM(H59:J59) -> 1764 | L59: P0001
A60: 45458 | B60: Aero0193 | C60: UIN Plate | D60: 1 | E60: K square Engineering | F60: 45458 | G60: 600 | H60: =D60*G60 -> 600 | I60: =0.18*H60 -> 108 | J60: 0 | K60: =SUM(H60:J60) -> 708 | L60: P0001
A61: 45460 | B61: Aero0169 | C61: PCB | D61: 1 | E61: APICO | F61: 45458 | G61: 347500 | H61: =D61*G61 -> 347500 | I61: =0.18*H61 -> 62550 | J61: 0 | K61: =SUM(H61:J61) -> 410050 | L61: P0001
A62: 45461 | B62: Aero0193 | C62: UIN Plate | D62: 1 | E62: K square Engineering | F62: 45461 | G62: 600 | H62: =G62*D62 -> 600 | I62: =0.18*H62 -> 108 | J62: 0 | K62: =SUM(H62:J62) -> 708 | L62: P0001
A63: 45462 | B63: Aero0195 | C63: =VLOOKUP(B63,'Component Master'!B:D,3,0) -> Servo cables-45 cm | D63: 6 | E63: Macfos | F63: 45460 | G63: 83.898 | H63: =G63*D63 -> 503.388 | I63: =0.18*H63 -> 90.60984 | J63: =124/2 -> 62 | K63: =SUM(H63:J63) -> 655.99784 | L63: P0001
A64: 45462 | B64: Aero0196 | C64: =VLOOKUP(B64,'Component Master'!B:D,3,0) -> Servo cables-60cm | D64: 6 | E64: Macfos | F64: 45460 | G64: 66.948 | H64: =G64*D64 -> 401.688 | I64: =0.18*H64 -> 72.30384 | J64: =124/2 -> 62 | K64: =SUM(H64:J64) -> 535.99184 | L64: P0001
A65: 45462 | B65: Aero0190 | C65: Void Stickers | D65: 200 | E65: Pio Printers Pvt Ltd | F65: 45462 | G65: 4.16 | H65: =G65*D65 -> 832 | I65: =0.18*H65 -> 149.76 | J65: 0 | K65: =SUM(H65:J65) -> 981.76 | L65: P0001
A66: 45467 | B66: Aero0029 | C66: Lug connector enclosing plate | D66: 2 | E66: AMUSE | F66: 45467 | G66: 296.7 | H66: 593.4 | I66: 106.812 | J66: 0 | K66: 700.212 | L66: AGRI-TC
A67: 45467 | B67: Aero0029 | C67: PCB Enclosure | D67: 2 | E67: AMUSE | F67: 45467 | G67: 2614.4 | H67: 5228.8 | I67: 941.184 | J67: 0 | K67: 6169.984 | L67: AGRI-TC
A68: 45467 | B68: Aero0183 | C68: 1/8 inch water flow sensor-YF-S401 | D68: 2 | E68: ZBOTICS | F68: 45462 | G68: 181 | H68: 362 | I68: 65.16 | J68: 120.36 | K68: 547.52 | L68: AGRI-TC
A69: 45467 | B69: Aero0198 | C69: Amass XT150 Gold plated Male/Female connector with High current(130A Max) | D69: 4 | E69: MACFOS LIMITED | F69: 45462 | G69: 111.1025 | H69: 444.41 | I69: 79.9938 | J69: 113 | K69: 637.4038 | L69: AGRI-TC
A70: 45467 | B70: Aero0199 | C70: Amass AS150 Anti spark Insulating Gold plated connector 1 pair | D70: 4 | E70: MACFOS LIMITED | F70: 45462 | G70: 465.255 | H70: 1861.02 | I70: 334.9836 | J70: 113 | K70: 2309.0036 | L70: AGRI-TC
A71: 45467 | B71: Aero0031 | C71: MK15 Remote controller | D71: 2 | E71: Elecdrone Technologies | F71: 45467 | G71: 39400 | H71: 78800 | I71: 14184 | J71: 0 | K71: 92984 | L71: AGRI-TC
A72: 45467 | B72: Aero0170 | C72: E610P frame with Tank | D72: 2 | E72: Elecdrone Technologies | F72: 45467 | G72: 42600 | H72: 85200 | I72: 4260 | J72: 0 | K72: 89460 | L72: AGRI-TC
A73: 45467 | B73: Aero0186 | C73: Tattu 6S 22000 mAh battery | D73: 4 | E73: Elecdrone Technologies | F73: 45467 | G73: 17700 | H73: 70800 | I73: 12744 | J73: 0 | K73: 83544 | L73: AGRI-TC
A74: 45467 | B74: Aero0064 | C74: Hobbywing X6 Plus 150KV motor CW combo | D74: 6 | E74: Elecdrone Technologies | F74: 45467 | G74: 10520 | H74: 63120 | I74: 3156 | J74: 0 | K74: 66276 | L74: AGRI-TC
A75: 45467 | B75: Aero0064 | C75: Hobbywing X6 Plus 150KV motor CW combo | D75: 6 | E75: Elecdrone Technologies | F75: 45467 | G75: 10520 | H75: 63120 | I75: 3156 | J75: 0 | K75: 66276 | L75: AGRI-TC
A76: 45467 | B76: Aero0057 | C76: SKYRC 1080W charger | D76: 2 | E76: Elecdrone Technologies | F76: 45467 | G76: 17000 | H76: 34000 | I76: 6120 | J76: 0 | K76: 40120 | L76: AGRI-TC
A77: 45467 | B77: Aero0110 | C77: Hobbywing 5LPM sprayer kit | D77: 2 | E77: Elecdrone Technologies | F77: 45467 | G77: 10200 | H77: 20400 | I77: 1020 | J77: 0 | K77: 21420 | L77: AGRI-TC
... A92: 45468 | B92: Aero0006 | C92: CF Sheet 300mm*300mm*1mm Thick | D92: 1 | E92: HINDUSTAN ENGINEERS | F92: 45468 | G92: 1162 | H92: 1162 | I92: 209.16 | J92: 0 | K92: 1371.16 | L92: AGRI-TC
A93: 45468 | B93: - | C93: Bricks | D93: 30 | E93: LOCAL | F93: - | G93: 12 | H93: =G93*D93 -> 360 | I93: 0 | J93: 0 | K93: =H93+I93+J93 -> 360 | L93: ALL
A94: 45469 | B94: Aero0173 | C94: Mauch 076 sensor | D94: 2 | E94: VYOM DRONES | F94: 45467 | G94: 4420 | H94: 8840 | I94: 442 | J94: 0 | K94: 9282 | L94: AGRI-TC
A95: 45469 | B95: Aero0181 | C95: Mauch BEC | D95: 2 | E95: VYOM DRONES | F95: 45467 | G95: 3900 | H95: 7800 | I95: 390 | J95: 0 | K95: 8190 | L95: AGRI-TC
A96: 45469 | B96: Aero0182 | C96: Mauch 086 Adapter cable for pixhawk | D96: 2 | E96: VYOM DRONES | F96: 45467 | G96: 500 | H96: 1000 | I96: 50 | J96: 0 | K96: 1050 | L96: AGRI-TC
A97: 45469 | B97: Aero0087 | C97: Cube Orange Plus with ADSB | D97: 2 | E97: VYOM DRONES | F97: 45467 | G97: 29000 | H97: 58000 | I97: 2900 | J97: 0 | K97: 60900 | L97: AGRI-TC
A98: 45469 | B98: Aero0092 | C98: Here 3+ GPS | D98: 2 | E98: VYOM DRONES | F98: 45467 | G98: 18750 | H98: 37500 | I98: 1875 | J98: 0 | K98: 39375 | L98: AGRI-TC
A99: 45469 | B99: - | C99: 50KG CI weight | D99: 2 | E99: Venkateswara weighing services | F99: 45469 | G99: 4300 | H99: =G99*D99 -> 8600 | I99: =0.18*H99 -> 1548 | J99: 0 | K99: =H99+I99+J99 -> 10148 | L99: ALL
A100: 45469 | B100: - | C100: 20KG CI weight | D100: 4 | E100: Venkateswara weighing services | F100: 45469 | G100: 1600 | H100: =G100*D100 -> 6400 | I100: =0.18*H100 -> 1152 | J100: 0 | K100: =H100+I100+J100 -> 7552 | L100: ALL
A101: 45471 | B101: Aero0027 | C101: Top Plate-water jet cutting | D101: 2 | E101: ALIND | F101: 45471 | G101: 1123 | H101: 2246 | I101: 112.3 | J101: 0 | K101: 2358.3 | L101: AGRI-TC
A102: 45471 | B102: Aero0027 | C102: Bottom Plate-Water jet cutting | D102: 2 | E102: ALIND | F102: 45471 | G102: 1149 | H102: 2298 | I102: 114.9 | J102: 0 | K102: 2412.9 | L102: AGRI-TC
A103: 45471 | B103: Aero0027 | C103: Collision sensor CF Plate-Water jet cutting | D103: 1 | E103: ALIND | F103: 45471 | G103: 542 | H103: 542 | I103: 27.1 | J103: 0 | K103: 569.1 | L103: AGRI-TC
A104: 45471 | B104: Aero0027 | C104: FC Platform plate-Water jet cutting | D104: 2 | E104: ALIND | F104: 45471 | G104: 353 | H104: 706 | I104: 35.3 | J104: 0 | K104: 741.3 | L104: AGRI-TC
A105: 45471 | B105: Aero0193 | C105: UIN Plate(2 nos) | D105: 1 | E105: K SQUARE ENGINEERING | F105: 45471 | G105: 700 | H105: 700 | I105: 126 | J105: 0 | K105: 826 | L105: AGRI-TC
A106: 45472 | B106: Aero0197 | C106: Sensor mounting plate | D106: 2 | E106: Nextgen | F106: 45472 | G106: 1500 | H106: 3000 | I106: 576 | J106: 200 | K106: =H106+I106+J106 -> 3776 | L106: P0001
A107: 45472 | B107: Aero0175 | C107: High Quality Ultra Flexible 8AWG Silicon Wire 1m (Black) | D107: 5 | E107: Elecdrone Technologies | F107: 45472 | G107: 370 | H107: 1850 | I107: 333 | J107: 0 | K107: 2183 | L107: ALL
A108: 45472 | B108: Aero0175 | C108: High Quality Ultra Flexible 8AWG Silicon Wire 1m (Red) | D108: 5 | E108: Elecdrone Technologies | F108: 45472 | G108: 370 | H108: 1850 | I108: 333 | J108: 0 | K108: 2183 | L108: ALL
A109: 45472 | B109: Aero0202 | C109: Telemetry cable | D109: 5 | E109: Elecdrone Technologies | F109: 45472 | G109: 385 | H109: 1925 | I109: 346.5 | J109: 0 | K109: 2271.5 | L109: ALL
A110: 45474 | B110: Aero0201 | C110: Crimping tool | D110: 1 | E110: Flipkart | F110: 45472 | G110: 444 | H110: =G110*D110 -> 444 | I110: 0 | J110: 0 | K110: =H110+I110+J110 -> 444 | L110: ALL
A111: 45474 | B111: Aero0204 | C111: Laser engraving on UIN plate | D111: 3 | E111: RC Laser tech | F111: 45474 | G111: 75 | H111: =G111*D111 -> 225 | I111: =0.18*H111 -> 40.5 | J111: 0 | K111: =H111+I111+J111 -> 265.5 | L111: P0001
A112: 45475 | B112: Aero0203 | C112: Brass Insert-OD 4.8mm(Pack of 25) | D112: 4 | E112: Macfos | F112: 45472 | G112: 58.47 | H112: =G112*D112 -> 233.88 | I112: =0.18*H112 -> 42.0984 | J112: 0 | K112: =H112+I112+J112 -> 275.9784 | L112: AGRI-TC
A113: 45477 | B113: Aero0193 | C113: UIN Plate | D113: 2 | E113: K Square Engineering | F113: 45477 | G113: 350 | H113: =G113*D113 -> 700 | I113: =0.18*H113 -> 126 | J113: 0 | K113: =H113+I113+J113 -> 826 | L113: P0001
A114: 45477 | B114: Aero0004 | C114: Agri Carry case | D114: 2 | E114: Aerotek | F114: 45477 | G114: 17500 | H114: =G114*D114 -> 35000 | I114: =0.18*H114 -> 6300 | J114: 0 | K114: =H114+I114+J114 -> 41300 | L114: AGRI-TC
...

Sheet Outward
A1: Date | B1: CID/SKU Number | C1: Client | D1: Client details | E1: Product | F1: Project
B2: Aero0001
B3: Aero0002
B4: Aero0003
B5: Aero0004
B6: Aero0005
B7: Aero0006
B8: Aero0007
B9: Aero0008
B10: Aero0009
B11: Aero0010
B12: Aero0011
B13: Aero0012
... B148: Aero0147

Sheet Workings
A1: S.No | B1: Date | C1: Vendor | D1: Total Price | E1: Project | F1: Remarks
A2: 1 | B2: 45425 | C2: Macfos | D2: =SUMIF('Order Tracker'!G2:G6,C2,'Order Tracker'!L2:L6) -> 59317.003 | E2: NRSC & AGRI-P0001 | F2: -
A3: 2 | B3: 45425 | C3: Hindustan Engineers | D3: =SUMIF('Order Tracker'!G3:G7,C3,'Order Tracker'!L3:L7) -> 11580.52 | E3: AGRI-P0001 | F3: -
A4: 3 | B4: 45425 | C4: Apico | D4: =SUMIF('Order Tracker'!G4:G8,C4,'Order Tracker'!L4:L8) -> 178180 | E4: AGRI-P0001 | F4: Payment processed for 75,000
A5: 4 | B5: 45426 | C5: Aerotek | D5: =SUMIF('Order Tracker'!G5:G9,C5,'Order Tracker'!L5:L9) -> 56640 | E5: AGRI-P0001
A6: 5 | B6: 45426 | C6: Vyom Drones | D6: =SUMIF('Order Tracker'!G6:G10,C6,'Order Tracker'!L6:L10) -> 23163 | E6: AGRI-P0001
A7: 6 | B7: 45427 | C7: Vyom Drones | D7: 9240 | E7: AGRI-P0001
A8: 7 | B8: 45427 | C8: Macfos | D8: 522 | E8: AGRI-P0001 | F8: Online order/COD
A9: 8 | B9: 45433 | C9: Apico | D9: 121625 | E9: AGRI-P0001
A10: 9 | B10: 45432 | C10: Nextgen | D10: 33335 | E10: AGRI-P0001 | F10: Material received
A11: 10 | B11: 45432 | C11: Amuse | D11: 6550.64 | E11: AGRI-P0001 | F11: Material received
A12: 11 | B12: 45435 | C12: Alind | D12: =SUMIF('Order Tracker'!G12:G103,C12,'Order Tracker'!L12:L1000) -> 13408.64 | E12: AGRI-P0001 | F12: Material received
A13: 12 | B13: 45435 | C13: Macfos | D13: =SUMIF('Order Tracker'!G13:G104,C13,'Order Tracker'!L13:L1001) -> 50775.748 | E13: AGRI-P0001 | F13: Online order/COD
A14: 13 | B14: 45435 | C14: Elecdrone Technologies | D14: =SUMIF('Order Tracker'!G14:G110,C14,'Order Tracker'!L14:L1002) -> 657549.92 | E14: AGRI-P0001 | F14: Material received
A15: 14 | B15: 45435 | C15: Aerotek | D15: =SUMIF('Order Tracker'!G15:G111,C15,'Order Tracker'!L15:L1003) -> 147618 | E15: AGRI-P0001 | F15: Carrycase & Aluminium mount-Material received - Payment from Aalayam Contructions
A16: 15 | B16: 45435 | C16: Apico | D16: 76000 | E16: AGRI-P0001 | F16: Project completed
A17: 16 | B17: 45436 | C17: Monotech | D17: =SUMIF('Order Tracker'!G17:G113,C17,'Order Tracker'!L17:L1005) -> 19381.5 | E17: AGRI-P0001 | F17: Payment from Aalayam constructions
A18: 17 | B18: 45436 | C18: Dynamic Calibration | D18: =SUMIF('Order Tracker'!G12:G120,C18,'Order Tracker'!L12:L1006) -> 6962 | E18: AGRI-P0001 | F18: Calibration Testing for measuring instruments
A19: 18 | B19: 45436 | C19: Elecdrone Technologies | D19: =SUMIF('Order Tracker'!G23:G121,C19,'Order Tracker'!L23:L1007) -> 663389.42 | E19: AGRI-P0001 | F19: PUMP
A20: 19 | B20: 45436 | C20: Alind | D20: =SUMIF('Order Tracker'!G24:G122,C20,'Order Tracker'!L24:L1008) -> 13021.12 | E20: AGRI-P0001 | F20: Top Plate
A21: 20 | B21: 45441 | C21: Apico | D21: 21835 | E21: AGRI-P0001 | F21: Material received/Payment from Aalayam constructions
A22: 21 | B22: 45441 | C22: Nextgen | D22: =SUMIF('Order Tracker'!G26:G124,C22,'Order Tracker'!L26:L1010) -> 135386.4 | E22: AGRI-P0001 | F22: Material received/Payment from Aalayam constructions
A23: 22 | B23: 45441 | C23: Amuse | D23: =SUMIF('Order Tracker'!G27:G125,C23,'Order Tracker'!L27:L1011) -> 12735.516 | E23: AGRI-P0001 | F23: Material received/Payment from Aalayam constructions
A24: 23 | B24: 45444 | C24: Alind | D24: =SUMIF('Order Tracker'!G28:G125,C24,'Order Tracker'!L28:L1012) -> 11789.12 | E24: AGRI-P0001 | F24: Material received
A25: 24 | B25: 45447 | C25: Elecdrone Technologies | D25: =SUMIF('Order Tracker'!G28:G125,C25,'Order Tracker'!L28:L1012) -> 657039.02 | E25: AGRI-P0001 | F25: Payment from Aalayam constructions
A26: 25 | B26: 45447 | C26: Macfos | D26: =SUMIF('Order Tracker'!G29:G125,C26,'Order Tracker'!L29:L1013) -> 47565.743 | E26: AGRI-P0001 | F26: Payment from Aalayam constructions
A27: 26 | B27: 45454 | C27: Elecdrone Technologies | D27: 5134.52 | E27: AGRI-P0001 | F27: Payment from Aalayam constructions
A28: 27 | B28: 45454 | C28: Apico | D28: 104250 | E28: AGRI-P0001 | F28: Payment from Aalayam constructions
A29: 28 | B29: 45454 | C29: Yaan Infotech | D29: 18738.4 | E29: Inventory | F29: For Label stickers
A30: 29 | B30: 45464 | C30: Dynamic Calibration | D30: 9204 | E30: AGRI-P0001 | F30: Calibration Testing for measuring instruments
A31: 30 | B31: 45464 | C31: Macfos | D31: 32719 | E31: AGRI-P0001 | F31: For Obstacle avoidance sensor ship it to PDRL

Sheet Notes
A1: Terms | B1: Full form/Understanding
A2: Yes | B2: Possibility of usage in the Drone
A3: No | B3: It will not be used in the Drone
A4: Numbers | B4: Defines the quantity, that will be used in the Drone
A5: Project Specific | B5: Depends on the project needs
A6: Availability | B6: It shows how much quantity is available in the Inventory
A7: P0001,P0002,P0003 | B7: Represents Materials assigned to the project

Sheet Flight test
A1: S.No | B1: Date | C1: Project | D1: Product | E1: Team Members | F1: Starting Time | G1: Return Time | H1: Cab Number | I1: Cab Driver Details | J1: Location | K1: Total Amount
A2: 1 | B2: 45490 | C2: P0002 | D2: CRRI | E2: Hari,Gokul,Balaji | F2: 7:10AM | G2: 0.89583333 | H2: TN05 CR9226 | I2: Prasanth- 6369940114 | J2: Nagari,Chittor | K2: 6960
A3: 2 | B3: 45491 | C3: P0006 | D3: BHIMA | E3: Balaji,Arun,Revanth,Gokul | F3: 10:00AM | G3: 7:30PM | H3: TN04 BD2431 | I3: Karthick-7358313385 | J3: Padappai | K3: 4200
A4: 3 | B4: 45491 | C4: P0006 | D4: BHIMA | E4: Balaji,Arun,Revanth,Gokul | F4: 10:00AM | G4: 7:30PM | H4: TN45 BK 0983 | I4: Selva-9600634465 | J4: Padappai | K4: 2250
A5: 4 | B5: 45493 | C5: P0006 | D5: BHIMA | E5: Balaji,Arun,Revanth,Gokul | F5: 7:10AM | G5: 5:00PM | H5: TN04 BD2431 | I5: Karthick-7358313385 | J5: Padappai | K5: 4200
A6: 5 | B6: 45493 | C6: P0006 | D6: BHIMA | E6: Balaji,Arun,Revanth,Gokul | F6: 7:10AM | G6: 5:00PM | H6: TN48 AR6286 | I6: Ram- 9384759298 | J6: Padappai | K6: 2750
A7: 6 | B7: 45493 | C7: P0006 | D7: BHIMA | E7: Santhosh & Client visit | F7: 12:30PM | G7: 5:00PM | H7: TN67 BQ6822 | I7: Ajmal- 7094623223 | J7: Padappai | K7: 3180
A8: 7 | B8: 45496 | C8: P0002 | D8: CRRI | E8: Deepak,Gokul,Balaji,Ganesnan | F8: 06:20AM | G8: 5:35PM | H8: TN06 C6526 | I8: Arul - 88385 70451 | J8: Nagari,Chittor | K8: 6850
A9: 8 | B9: 45497 | C9: P0006 | D9: BHIMA & CRRI | E9: Balaji, Gokul, Aksash & Hari | F9: 06:30AM | G9: 03:30PM | H9: TN 48 BH0750 | I9: Raj Kumar- 9884847827 | J9: Padappai | K9: 2450
A10: 9 | B10: 45497 | C10: P0006 | D10: BHIMA | E10: Balaji,Arun,Revanth,Gokul | F10: 7:10AM | G10: 5:00PM | H10: TN04 BD2431 | I10: Karthick-7358313385 | J10: Padappai | K10: 4200
A11: 10 | B11: 45500 | C11: P0006 | D11: BHIMA | E11: Gokul,Arun,Revanth & Exicom team | F11: 7:10AM | G11: 7:40PM | H11: TN22CJ8048 | I11: Vijayakumar-9786039559 | J11: Padappai | K11: 4550
A12: 11 | B12: 45500 | C12: P0006 | D12: BHIMA | E12: Gokul,Arun,Revanth & Exicom team | F12: 7:10AM | G12: 7:40PM | H12: TN04 BD2431 | I12: Karthick-7358313385 | J12: Padappai | K12: 4200
A13: 12 | B13: 45504 | C13: P0006 | D13: BHIMA & CRRI | E13: Balaji, Arun, Hari, Vedanth & Akash | F13: 0.27083333 | G13: 03:35PM | H13: TN48 AR6286 | I13: Ram- 9384759298 | J13: Padappai | K13: 2750
A14: 13 | B14: 45504 | C14: P0006 | D14: BHIMA & CRRI | E14: Balaji, Arun, Hari, Vedanth & Akash | F14: 0.27083333 | G14: 03:35PM | H14: TN04 BD2431 | I14: Karthick-7358313385 | J14: Padappai | K14: 4200
A15: 14 | B15: 45507 | C15: P0002 | D15: CRRI | E15: Balaji,Gokul,Deepak and Sumit(CRRI) | F15: 06:50AM | G15: 9:30PM | H15: TN06M 3056 | I15: Pradeep- 9597856428 | J15: Nagari,Chittor | K15: 6910

Sheet Tables
A1: Inventory | C1: BOM product list
A2: SKU | B2: Qty | C2: SKU | D2: Qty
H110: Airframe
H111: Communication
H112: Electricals
H113: Electronics
H114: Payload
E206: Airframe
E207: Airframe
E208: Airframe
E209: Airframe
E210: Airframe
E211: Airframe
E212: Electronics
E213: Electronics
E214: Electronics
E215: Airframe
E216: Airframe
E217: Airframe
... E237: Electricals
